{
    "walls": [
        {"_id":"v6dhc7rF8Sbl799Q","c":[2600,4250,2600,4200],"move":20,"sound":20,"dir":0,"door":0,"ds":0,"flags":{},"sight":20,"light":20,"threshold":{"light":null,"sight":null,"sound":null,"attenuation":false}},
        {"_id":"3PmBkmma4ZNKU1nQ","c":[2600,4200,1987,4200],"move":20,"sound":20,"dir":0,"door":0,"ds":0,"flags":{},"sight":20,"light":20,"threshold":{"light":null,"sight":null,"sound":null,"attenuation":false}},
        {"_id":"Y3YUijK28Y7SSSQC","c":[1987,4200,1987,3587],"move":20,"sound":20,"dir":0,"door":0,"ds":0,"flags":{},"sight":20,"light":20,"threshold":{"light":null,"sight":null,"sound":null,"attenuation":false}},
        {"_id":"zkM6PWUFS1cfj3s0","c":[1987,3587,2600,3587],"move":20,"sound":20,"dir":0,"door":0,"ds":0,"flags":{},"sight":20,"light":20,"threshold":{"light":null,"sight":null,"sound":null,"attenuation":false}},
        {"_id":"b5uiGpzmGY6E6hMr","c":[2600,3587,2600,3550],"move":20,"sound":20,"dir":0,"door":0,"ds":0,"flags":{},"sight":20,"light":20,"threshold":{"light":null,"sight":null,"sound":null,"attenuation":false}},
        {"_id":"uIxhcxWhzfStzBsV","c":[2600,3550,2600,3500],"move":20,"sound":20,"dir":0,"door":0,"ds":0,"flags":{},"sight":20,"light":20,"threshold":{"light":null,"sight":null,"sound":null,"attenuation":false}},
        {"_id":"pWLjQrzs9fiVA4ui","c":[2600,3500,1600,3500],"move":20,"sound":20,"dir":0,"door":0,"ds":0,"flags":{},"sight":20,"light":20,"threshold":{"light":null,"sight":null,"sound":null,"attenuation":false}},
        {"_id":"AAt0gs14OPhM9Z1a","c":[1600,3500,1600,2700],"move":20,"sound":20,"dir":0,"door":0,"ds":0,"flags":{},"sight":20,"light":20,"threshold":{"light":null,"sight":null,"sound":null,"attenuation":false}},
        {"_id":"MoXc2t2QxWPjvkuL","c":[1600,2700,1575,2700],"move":20,"sound":20,"dir":0,"door":0,"ds":0,"flags":{},"sight":20,"light":20,"threshold":{"light":null,"sight":null,"sound":null,"attenuation":false}},
        {"_id":"xcSYnq7b2vSgoxWl","c":[1575,2700,1500,2700],"move":20,"sound":20,"dir":0,"door":0,"ds":0,"flags":{},"sight":20,"light":20,"threshold":{"light":null,"sight":null,"sound":null,"attenuation":false}},
        {"_id":"5eaU3W5CLxyg3Dwy","c":[1500,2700,1500,3587],"move":20,"sound":20,"dir":0,"door":0,"ds":0,"flags":{},"sight":20,"light":20,"threshold":{"light":null,"sight":null,"sound":null,"attenuation":false}},
        {"_id":"lH4ssppcHq3ouu8K","c":[1500,3587,1900,3587],"move":20,"sound":20,"dir":0,"door":0,"ds":0,"flags":{},"sight":20,"light":20,"threshold":{"light":null,"sight":null,"sound":null,"attenuation":false}},
        {"_id":"i6Mr4zThCybvYmzr","c":[1900,3587,1900,4287],"move":20,"sound":20,"dir":0,"door":0,"ds":0,"flags":{},"sight":20,"light":20,"threshold":{"light":null,"sight":null,"sound":null,"attenuation":false}},
        {"_id":"Y4KH6j7bIlt2s0WY","c":[1900,4287,2600,4287],"move":20,"sound":20,"dir":0,"door":0,"ds":0,"flags":{},"sight":20,"light":20,"threshold":{"light":null,"sight":null,"sound":null,"attenuation":false}},
        {"_id":"isqlrzr85oByUUlz","c":[2600,4287,2600,4250],"move":20,"sound":20,"dir":0,"door":0,"ds":0,"flags":{},"sight":20,"light":20,"threshold":{"light":null,"sight":null,"sound":null,"attenuation":false}},
        {"_id":"mV3iKmjTZT0uU8Zt","c":[2600,3550,2625,3550],"move":20,"sound":20,"dir":0,"door":0,"ds":0,"flags":{},"sight":20,"light":20,"threshold":{"light":null,"sight":null,"sound":null,"attenuation":false}},
        {"_id":"pKrH8tiDyknzY2I1","c":[2775,3550,2800,3550],"move":20,"sound":20,"dir":0,"door":0,"ds":0,"flags":{},"sight":20,"light":20,"threshold":{"light":null,"sight":null,"sound":null,"attenuation":false}},
        {"_id":"KrXvkBh1ZDZARy3G","c":[2800,3550,2800,3525],"move":20,"sound":20,"dir":0,"door":0,"ds":0,"flags":{},"sight":20,"light":20,"threshold":{"light":null,"sight":null,"sound":null,"attenuation":false}},
        {"_id":"yBWNpbDdjJYCUpIl","c":[2800,3525,2812,3525],"move":20,"sound":20,"dir":0,"door":0,"ds":0,"flags":{},"sight":20,"light":20,"threshold":{"light":null,"sight":null,"sound":null,"attenuation":false}},
        {"_id":"WYWQwsx2bNZbMtV2","c":[2812,3500,3000,3500],"move":20,"sound":20,"dir":0,"door":0,"ds":0,"flags":{},"sight":20,"light":20,"threshold":{"light":null,"sight":null,"sound":null,"attenuation":false}},
        {"_id":"XqfpHQACpgyYuXHL","c":[3000,3500,3000,3000],"move":20,"sound":20,"dir":0,"door":0,"ds":0,"flags":{},"sight":20,"light":20,"threshold":{"light":null,"sight":null,"sound":null,"attenuation":false}},
        {"_id":"dMyJk5KVKFHMxcZr","c":[3000,3000,3200,3000],"move":20,"sound":20,"dir":0,"door":0,"ds":0,"flags":{},"sight":20,"light":20,"threshold":{"light":null,"sight":null,"sound":null,"attenuation":false}},
        {"_id":"4thZ6o2hswFTCBzm","c":[3200,3000,3200,3050],"move":20,"sound":20,"dir":0,"door":0,"ds":0,"flags":{},"sight":20,"light":20,"threshold":{"light":null,"sight":null,"sound":null,"attenuation":false}},
        {"_id":"gM29z6WYZdCw0cN3","c":[3200,3050,3200,3087],"move":20,"sound":20,"dir":0,"door":0,"ds":0,"flags":{},"sight":20,"light":20,"threshold":{"light":null,"sight":null,"sound":null,"attenuation":false}},
        {"_id":"KskiyfzmPuBhANHL","c":[3200,3087,3100,3087],"move":20,"sound":20,"dir":0,"door":0,"ds":0,"flags":{},"sight":20,"light":20,"threshold":{"light":null,"sight":null,"sound":null,"attenuation":false}},
        {"_id":"FWcdNIaFCUeJLNOz","c":[3100,3087,3100,3512],"move":20,"sound":20,"dir":0,"door":0,"ds":0,"flags":{},"sight":20,"light":20,"threshold":{"light":null,"sight":null,"sound":null,"attenuation":false}},
        {"_id":"8GOdSnSaAHlOYlfl","c":[3100,3512,3912,3512],"move":20,"sound":20,"dir":0,"door":0,"ds":0,"flags":{},"sight":20,"light":20,"threshold":{"light":null,"sight":null,"sound":null,"attenuation":false}},
        {"_id":"tRU209VwZjoGoY5q","c":[3912,3512,3912,3100],"move":20,"sound":20,"dir":0,"door":0,"ds":0,"flags":{},"sight":20,"light":20,"threshold":{"light":null,"sight":null,"sound":null,"attenuation":false}},
        {"_id":"YLNdzmfsfOx9RvZ1","c":[3912,3100,3312,3100],"move":20,"sound":20,"dir":0,"door":0,"ds":0,"flags":{},"sight":20,"light":20,"threshold":{"light":null,"sight":null,"sound":null,"attenuation":false}},
        {"_id":"NOec3h9Ibgl86shv","c":[3312,3100,3312,3050],"move":20,"sound":20,"dir":0,"door":0,"ds":0,"flags":{},"sight":20,"light":20,"threshold":{"light":null,"sight":null,"sound":null,"attenuation":false}},
        {"_id":"vLb8sl2U6icNr4UI","c":[3312,3050,3312,3012],"move":20,"sound":20,"dir":0,"door":0,"ds":0,"flags":{},"sight":20,"light":20,"threshold":{"light":null,"sight":null,"sound":null,"attenuation":false}},
        {"_id":"52SbfANB5eN6tDCZ","c":[3312,3012,3600,3012],"move":20,"sound":20,"dir":0,"door":0,"ds":0,"flags":{},"sight":20,"light":20,"threshold":{"light":null,"sight":null,"sound":null,"attenuation":false}},
        {"_id":"ME6ToXHrAhohcN5y","c":[3600,3012,3600,2800],"move":20,"sound":20,"dir":0,"door":0,"ds":0,"flags":{},"sight":20,"light":20,"threshold":{"light":null,"sight":null,"sound":null,"attenuation":false}},
        {"_id":"0UVM6JBdNg6lnWsc","c":[3600,2800,3662,2800],"move":20,"sound":20,"dir":0,"door":0,"ds":0,"flags":{},"sight":20,"light":20,"threshold":{"light":null,"sight":null,"sound":null,"attenuation":false}},
        {"_id":"GqZsUaQBEvFODZeG","c":[3662,2800,3700,2800],"move":20,"sound":20,"dir":0,"door":0,"ds":0,"flags":{},"sight":20,"light":20,"threshold":{"light":null,"sight":null,"sound":null,"attenuation":false}},
        {"_id":"3UuvZpMARbXPq9YJ","c":[3700,2800,3700,3012],"move":20,"sound":20,"dir":0,"door":0,"ds":0,"flags":{},"sight":20,"light":20,"threshold":{"light":null,"sight":null,"sound":null,"attenuation":false}},
        {"_id":"TQt2cQOIz98bGSFH","c":[3700,3012,3975,3012],"move":20,"sound":20,"dir":0,"door":0,"ds":0,"flags":{},"sight":20,"light":20,"threshold":{"light":null,"sight":null,"sound":null,"attenuation":false}},
        {"_id":"HoUDPojTcvLtU7BG","c":[3975,3012,3975,4287],"move":20,"sound":20,"dir":0,"door":0,"ds":0,"flags":{},"sight":20,"light":20,"threshold":{"light":null,"sight":null,"sound":null,"attenuation":false}},
        {"_id":"ZCWzBgEu41fomOU3","c":[3975,4287,2812,4300],"move":20,"sound":20,"dir":0,"door":0,"ds":0,"flags":{},"sight":20,"light":20,"threshold":{"light":null,"sight":null,"sound":null,"attenuation":false}},
        {"_id":"aIQoYpMVNyJQG2h7","c":[2812,4300,2812,4250],"move":20,"sound":20,"dir":0,"door":0,"ds":0,"flags":{},"sight":20,"light":20,"threshold":{"light":null,"sight":null,"sound":null,"attenuation":false}},
        {"_id":"bmdlCgRsMmv9z3pr","c":[2812,4250,2812,4200],"move":20,"sound":20,"dir":0,"door":0,"ds":0,"flags":{},"sight":20,"light":20,"threshold":{"light":null,"sight":null,"sound":null,"attenuation":false}},
        {"_id":"Ar0sSKCkUuc0QcBi","c":[2812,4200,3912,4200],"move":20,"sound":20,"dir":0,"door":0,"ds":0,"flags":{},"sight":20,"light":20,"threshold":{"light":null,"sight":null,"sound":null,"attenuation":false}},
        {"_id":"BbG3gsnsQpGKOOq1","c":[3912,4200,3912,3587],"move":20,"sound":20,"dir":0,"door":0,"ds":0,"flags":{},"sight":20,"light":20,"threshold":{"light":null,"sight":null,"sound":null,"attenuation":false}},
        {"_id":"Yi2ccQq2i1h1B8x9","c":[3912,3587,2800,3587],"move":20,"sound":20,"dir":0,"door":0,"ds":0,"flags":{},"sight":20,"light":20,"threshold":{"light":null,"sight":null,"sound":null,"attenuation":false}},
        {"_id":"mQl6QPcB0X2lzWzz","c":[2800,3587,2800,3550],"move":20,"sound":20,"dir":0,"door":0,"ds":0,"flags":{},"sight":20,"light":20,"threshold":{"light":null,"sight":null,"sound":null,"attenuation":false}},
        {"_id":"GWEYXBR5BkUVzjzv","c":[2812,3525,2812,3500],"move":20,"sound":20,"dir":0,"door":0,"ds":0,"flags":{},"sight":20,"light":20,"threshold":{"light":null,"sight":null,"sound":null,"attenuation":false}},
        {"_id":"vqAWG3N99oFFAxUQ","c":[2625,4250,2700,4250],"move":20,"sound":20,"dir":0,"door":1,"ds":0,"flags":{},"sight":20,"light":20,"threshold":{"light":null,"sight":null,"sound":null,"attenuation":false}},
        {"_id":"YHkKqT2cU0REWhfX","c":[2700,4250,2775,4250],"move":20,"sound":20,"dir":0,"door":1,"ds":0,"flags":{},"sight":20,"light":20,"threshold":{"light":null,"sight":null,"sound":null,"attenuation":false}},
        {"_id":"X0mZkutzjYY7YWRs","c":[2625,3550,2700,3550],"move":20,"sound":20,"dir":0,"door":1,"ds":0,"flags":{},"sight":20,"light":20,"threshold":{"light":null,"sight":null,"sound":null,"attenuation":false}},
        {"_id":"Vq11MqDpdKag2rCQ","c":[2700,3550,2775,3550],"move":20,"sound":20,"dir":0,"door":1,"ds":0,"flags":{},"sight":20,"light":20,"threshold":{"light":null,"sight":null,"sound":null,"attenuation":false}},
        {"_id":"hLe629ba2ICleIrw","c":[2600,4250,2625,4250],"move":20,"sound":20,"dir":0,"door":0,"ds":0,"flags":{},"sight":20,"light":20,"threshold":{"light":null,"sight":null,"sound":null,"attenuation":false}},
        {"_id":"fKYObnSiFtpSTIdF","c":[2775,4250,2812,4250],"move":20,"sound":20,"dir":0,"door":0,"ds":0,"flags":{},"sight":20,"light":20,"threshold":{"light":null,"sight":null,"sound":null,"attenuation":false}},
        {"_id":"uXvpteckYCYe0Grk","c":[3200,3050,3312,3050],"move":20,"sound":20,"dir":0,"door":1,"ds":0,"flags":{},"sight":20,"light":20,"threshold":{"light":null,"sight":null,"sound":null,"attenuation":false}},
        {"_id":"G2rNq4hMO2KmitPC","c":[3662,2775,3662,2700],"move":20,"sound":20,"dir":0,"door":1,"ds":0,"flags":{},"sight":20,"light":20,"threshold":{"light":null,"sight":null,"sound":null,"attenuation":false}},
        {"_id":"XIm4RRcIfqhzdQfP","c":[3662,2700,3662,2625],"move":20,"sound":20,"dir":0,"door":1,"ds":0,"flags":{},"sight":20,"light":20,"threshold":{"light":null,"sight":null,"sound":null,"attenuation":false}},
        {"_id":"WeoB4ONJgJQUfLfc","c":[3662,2775,3662,2800],"move":20,"sound":20,"dir":0,"door":0,"ds":0,"flags":{},"sight":20,"light":20,"threshold":{"light":null,"sight":null,"sound":null,"attenuation":false}},
        {"_id":"gNFlugIValxNfMdA","c":[3662,2625,3662,2600],"move":20,"sound":20,"dir":0,"door":0,"ds":0,"flags":{},"sight":20,"light":20,"threshold":{"light":null,"sight":null,"sound":null,"attenuation":false}},
        {"_id":"lX54mTqnzvO2aBCF","c":[3662,2600,3612,2600],"move":20,"sound":20,"dir":0,"door":0,"ds":0,"flags":{},"sight":20,"light":20,"threshold":{"light":null,"sight":null,"sound":null,"attenuation":false}},
        {"_id":"W7bTBpc5JMYnlcVX","c":[3612,2600,3612,2487],"move":20,"sound":20,"dir":0,"door":0,"ds":0,"flags":{},"sight":20,"light":20,"threshold":{"light":null,"sight":null,"sound":null,"attenuation":false}},
        {"_id":"KUMlEbaaM7jnzVvY","c":[3612,2487,3500,2487],"move":20,"sound":20,"dir":0,"door":0,"ds":0,"flags":{},"sight":20,"light":20,"threshold":{"light":null,"sight":null,"sound":null,"attenuation":false}},
        {"_id":"wKzdoZbqR1p09Og3","c":[3500,2487,3500,2462],"move":20,"sound":20,"dir":0,"door":0,"ds":0,"flags":{},"sight":20,"light":20,"threshold":{"light":null,"sight":null,"sound":null,"attenuation":false}},
        {"_id":"L3gwQ47eH8mM01Dy","c":[3500,2462,3500,2400],"move":20,"sound":20,"dir":0,"door":0,"ds":0,"flags":{},"sight":20,"light":20,"threshold":{"light":null,"sight":null,"sound":null,"attenuation":false}},
        {"_id":"KJAJMoyuqlMmPbfD","c":[3500,2400,3700,2400],"move":20,"sound":20,"dir":0,"door":0,"ds":0,"flags":{},"sight":20,"light":20,"threshold":{"light":null,"sight":null,"sound":null,"attenuation":false}},
        {"_id":"3F69qdaa2agfCxTo","c":[3700,2400,3700,2087],"move":20,"sound":20,"dir":0,"door":0,"ds":0,"flags":{},"sight":20,"light":20,"threshold":{"light":null,"sight":null,"sound":null,"attenuation":false}},
        {"_id":"hD4gVMatEjOiRdpH","c":[3700,2087,3337,2087],"move":20,"sound":20,"dir":0,"door":0,"ds":0,"flags":{},"sight":20,"light":20,"threshold":{"light":null,"sight":null,"sound":null,"attenuation":false}},
        {"_id":"Iuc5rusoNrqVYyV5","c":[3337,2087,3325,2037],"move":20,"sound":20,"dir":0,"door":0,"ds":0,"flags":{},"sight":20,"light":20,"threshold":{"light":null,"sight":null,"sound":null,"attenuation":false}},
        {"_id":"NLioSg30CcNjhNaf","c":[3325,2037,3325,2000],"move":20,"sound":20,"dir":0,"door":0,"ds":0,"flags":{},"sight":20,"light":20,"threshold":{"light":null,"sight":null,"sound":null,"attenuation":false}},
        {"_id":"N8IqLvWCrhgDg92K","c":[3325,2000,3700,2000],"move":20,"sound":20,"dir":0,"door":0,"ds":0,"flags":{},"sight":20,"light":20,"threshold":{"light":null,"sight":null,"sound":null,"attenuation":false}},
        {"_id":"FLw61lKGVMlgUVez","c":[3700,2000,3700,1200],"move":20,"sound":20,"dir":0,"door":0,"ds":0,"flags":{},"sight":20,"light":20,"threshold":{"light":null,"sight":null,"sound":null,"attenuation":false}},
        {"_id":"OY8vsHZt9KI3q57G","c":[3700,1200,3787,1200],"move":20,"sound":20,"dir":0,"door":0,"ds":0,"flags":{},"sight":20,"light":20,"threshold":{"light":null,"sight":null,"sound":null,"attenuation":false}},
        {"_id":"9dBOwdxqUVf0nsfx","c":[3787,1200,3787,2487],"move":20,"sound":20,"dir":0,"door":0,"ds":0,"flags":{},"sight":20,"light":20,"threshold":{"light":null,"sight":null,"sound":null,"attenuation":false}},
        {"_id":"5xIOZJHR9R3EaCSQ","c":[3787,2487,3700,2487],"move":20,"sound":20,"dir":0,"door":0,"ds":0,"flags":{},"sight":20,"light":20,"threshold":{"light":null,"sight":null,"sound":null,"attenuation":false}},
        {"_id":"rxq9hDZEqGY0WcM6","c":[3700,2487,3700,2600],"move":20,"sound":20,"dir":0,"door":0,"ds":0,"flags":{},"sight":20,"light":20,"threshold":{"light":null,"sight":null,"sound":null,"attenuation":false}},
        {"_id":"EuDW8JRLdZ2fnk6V","c":[3700,2600,3662,2600],"move":20,"sound":20,"dir":0,"door":0,"ds":0,"flags":{},"sight":20,"light":20,"threshold":{"light":null,"sight":null,"sound":null,"attenuation":false}},
        {"_id":"fETdWCevOQHcpdqH","c":[3500,2462,3475,2462],"move":20,"sound":20,"dir":0,"door":0,"ds":0,"flags":{},"sight":20,"light":20,"threshold":{"light":null,"sight":null,"sound":null,"attenuation":false}},
        {"_id":"uhw96Ru0LCmX2rYy","c":[3325,2037,3287,2037],"move":20,"sound":20,"dir":0,"door":0,"ds":0,"flags":{},"sight":20,"light":20,"threshold":{"light":null,"sight":null,"sound":null,"attenuation":false}},
        {"_id":"6vOkKMwMB8COxQmn","c":[3137,2037,3100,2037],"move":20,"sound":20,"dir":0,"door":0,"ds":0,"flags":{},"sight":20,"light":20,"threshold":{"light":null,"sight":null,"sound":null,"attenuation":false}},
        {"_id":"Dy7f8PLJEtmoap4i","c":[3100,2037,3100,2000],"move":20,"sound":20,"dir":0,"door":0,"ds":0,"flags":{},"sight":20,"light":20,"threshold":{"light":null,"sight":null,"sound":null,"attenuation":false}},
        {"_id":"KvQMeHruTbYurDqE","c":[3100,2000,2612,2000],"move":20,"sound":20,"dir":0,"door":0,"ds":0,"flags":{},"sight":20,"light":20,"threshold":{"light":null,"sight":null,"sound":null,"attenuation":false}},
        {"_id":"Za2yIcG87hcUFpLj","c":[2612,2000,2612,2037],"move":20,"sound":20,"dir":0,"door":0,"ds":0,"flags":{},"sight":20,"light":20,"threshold":{"light":null,"sight":null,"sound":null,"attenuation":false}},
        {"_id":"p7cUR9z6QQBvAbmW","c":[2612,2037,2612,2087],"move":20,"sound":20,"dir":0,"door":0,"ds":0,"flags":{},"sight":20,"light":20,"threshold":{"light":null,"sight":null,"sound":null,"attenuation":false}},
        {"_id":"H0iRW3PcEMNtI0ee","c":[2612,2087,3100,2087],"move":20,"sound":20,"dir":0,"door":0,"ds":0,"flags":{},"sight":20,"light":20,"threshold":{"light":null,"sight":null,"sound":null,"attenuation":false}},
        {"_id":"MUKirIH5dQGL6hXT","c":[3100,2087,3100,2037],"move":20,"sound":20,"dir":0,"door":0,"ds":0,"flags":{},"sight":20,"light":20,"threshold":{"light":null,"sight":null,"sound":null,"attenuation":false}},
        {"_id":"lxIHBJd62Zz2VxNk","c":[2612,2037,2587,2037],"move":20,"sound":20,"dir":0,"door":0,"ds":0,"flags":{},"sight":20,"light":20,"threshold":{"light":null,"sight":null,"sound":null,"attenuation":false}},
        {"_id":"OkEqxoa4sj38Tz4B","c":[2425,2037,2400,2037],"move":20,"sound":20,"dir":0,"door":0,"ds":0,"flags":{},"sight":20,"light":20,"threshold":{"light":null,"sight":null,"sound":null,"attenuation":false}},
        {"_id":"83RB7C6zrnxNArQg","c":[2400,2037,2400,2000],"move":20,"sound":20,"dir":0,"door":0,"ds":0,"flags":{},"sight":20,"light":20,"threshold":{"light":null,"sight":null,"sound":null,"attenuation":false}},
        {"_id":"pktUu33tHTcqHVQG","c":[2400,2000,1600,2000],"move":20,"sound":20,"dir":0,"door":0,"ds":0,"flags":{},"sight":20,"light":20,"threshold":{"light":null,"sight":null,"sound":null,"attenuation":false}},
        {"_id":"VLBPRlfV4KliVEuC","c":[1600,2000,1600,1600],"move":20,"sound":20,"dir":0,"door":0,"ds":0,"flags":{},"sight":20,"light":20,"threshold":{"light":null,"sight":null,"sound":null,"attenuation":false}},
        {"_id":"xdNXdIDeTi76trn3","c":[1600,1600,1512,1600],"move":20,"sound":20,"dir":0,"door":0,"ds":0,"flags":{},"sight":20,"light":20,"threshold":{"light":null,"sight":null,"sound":null,"attenuation":false}},
        {"_id":"CegyzgNJvfqzYMEr","c":[1512,1600,1512,2587],"move":20,"sound":20,"dir":0,"door":0,"ds":0,"flags":{},"sight":20,"light":20,"threshold":{"light":null,"sight":null,"sound":null,"attenuation":false}},
        {"_id":"vM0WPvKABdOsPJO9","c":[1575,2587,1600,2587],"move":20,"sound":20,"dir":0,"door":0,"ds":0,"flags":{},"sight":20,"light":20,"threshold":{"light":null,"sight":null,"sound":null,"attenuation":false}},
        {"_id":"Dg8Sf09OFZKNjnCr","c":[1600,2587,1600,2087],"move":20,"sound":20,"dir":0,"door":0,"ds":0,"flags":{},"sight":20,"light":20,"threshold":{"light":null,"sight":null,"sound":null,"attenuation":false}},
        {"_id":"YfWYVX7QHFvL9bEm","c":[1600,2087,2300,2087],"move":20,"sound":20,"dir":0,"door":0,"ds":0,"flags":{},"sight":20,"light":20,"threshold":{"light":null,"sight":null,"sound":null,"attenuation":false}},
        {"_id":"izxvvuOZk6L6XYlN","c":[2300,2087,2300,2337],"move":20,"sound":20,"dir":0,"door":0,"ds":0,"flags":{},"sight":20,"light":20,"threshold":{"light":null,"sight":null,"sound":null,"attenuation":false}},
        {"_id":"XEnvvqiy2q6BALHL","c":[2300,2337,2325,2337],"move":20,"sound":20,"dir":0,"door":0,"ds":0,"flags":{},"sight":20,"light":20,"threshold":{"light":null,"sight":null,"sound":null,"attenuation":false}},
        {"_id":"9at5dehvHqwxp47n","c":[2325,2337,2325,2275],"move":20,"sound":20,"dir":0,"door":0,"ds":0,"flags":{},"sight":20,"light":20,"threshold":{"light":null,"sight":null,"sound":null,"attenuation":false}},
        {"_id":"aYebbELrUmLPf34c","c":[2325,2275,2350,2262],"move":20,"sound":20,"dir":0,"door":0,"ds":0,"flags":{},"sight":20,"light":20,"threshold":{"light":null,"sight":null,"sound":null,"attenuation":false}},
        {"_id":"pvMG1wgm6xJPM3yy","c":[2350,2262,2400,2262],"move":20,"sound":20,"dir":0,"door":0,"ds":0,"flags":{},"sight":20,"light":20,"threshold":{"light":null,"sight":null,"sound":null,"attenuation":false}},
        {"_id":"sSkDlQETRHHBMMcu","c":[2400,2262,2400,2037],"move":20,"sound":20,"dir":0,"door":0,"ds":0,"flags":{},"sight":20,"light":20,"threshold":{"light":null,"sight":null,"sound":null,"attenuation":false}},
        {"_id":"sW2O5Bx8HRP1reOm","c":[2425,2037,2512,2037],"move":20,"sound":20,"dir":0,"door":1,"ds":0,"flags":{},"sight":20,"light":20,"threshold":{"light":null,"sight":null,"sound":null,"attenuation":false}},
        {"_id":"iK1FZSFKxB9mqsAN","c":[2512,2037,2587,2037],"move":20,"sound":20,"dir":0,"door":1,"ds":0,"flags":{},"sight":20,"light":20,"threshold":{"light":null,"sight":null,"sound":null,"attenuation":false}},
        {"_id":"CyjSJtmxyE9F0fHY","c":[3137,2037,3212,2037],"move":20,"sound":20,"dir":0,"door":1,"ds":0,"flags":{},"sight":20,"light":20,"threshold":{"light":null,"sight":null,"sound":null,"attenuation":false}},
        {"_id":"ganSaUEbWlY7E1G0","c":[3212,2037,3287,2037],"move":20,"sound":20,"dir":0,"door":1,"ds":0,"flags":{},"sight":20,"light":20,"threshold":{"light":null,"sight":null,"sound":null,"attenuation":false}},
        {"_id":"XzRTs05kmwOa4gzu","c":[3475,2462,3400,2462],"move":20,"sound":20,"dir":0,"door":1,"ds":0,"flags":{},"sight":20,"light":20,"threshold":{"light":null,"sight":null,"sound":null,"attenuation":false}},
        {"_id":"NX0CACwyRISMKDkD","c":[3400,2462,3325,2462],"move":20,"sound":20,"dir":0,"door":1,"ds":0,"flags":{},"sight":20,"light":20,"threshold":{"light":null,"sight":null,"sound":null,"attenuation":false}},
        {"_id":"88XGbvksa3135Vt8","c":[3325,2462,3287,2462],"move":20,"sound":20,"dir":0,"door":0,"ds":0,"flags":{},"sight":20,"light":20,"threshold":{"light":null,"sight":null,"sound":null,"attenuation":false}},
        {"_id":"o9Hyr3JETISxZiwR","c":[3287,2462,3262,2462],"move":20,"sound":20,"dir":0,"door":0,"ds":0,"flags":{},"sight":20,"light":20,"threshold":{"light":null,"sight":null,"sound":null,"attenuation":false}},
        {"_id":"HmQsrbNhuoQVNB2P","c":[3262,2462,3262,2500],"move":20,"sound":20,"dir":0,"door":0,"ds":0,"flags":{},"sight":20,"light":20,"threshold":{"light":null,"sight":null,"sound":null,"attenuation":false}},
        {"_id":"Jq1SYgCxdjE2WNMD","c":[3262,2500,2525,2500],"move":20,"sound":20,"dir":0,"door":0,"ds":0,"flags":{},"sight":20,"light":20,"threshold":{"light":null,"sight":null,"sound":null,"attenuation":false}},
        {"_id":"jzwEsQakq19iEsX3","c":[2525,2500,2500,2550],"move":20,"sound":20,"dir":0,"door":0,"ds":0,"flags":{},"sight":20,"light":20,"threshold":{"light":null,"sight":null,"sound":null,"attenuation":false}},
        {"_id":"fbaJOOGioFS6uxhK","c":[2500,2550,2450,2525],"move":20,"sound":20,"dir":0,"door":0,"ds":0,"flags":{},"sight":20,"light":20,"threshold":{"light":null,"sight":null,"sound":null,"attenuation":false}},
        {"_id":"tEOhFgthdrDMemvt","c":[2450,2525,2512,2450],"move":20,"sound":20,"dir":0,"door":0,"ds":0,"flags":{},"sight":20,"light":20,"threshold":{"light":null,"sight":null,"sound":null,"attenuation":false}},
        {"_id":"VFxCHyxoWZvGMqr2","c":[2512,2450,2512,2412],"move":20,"sound":20,"dir":0,"door":0,"ds":0,"flags":{},"sight":20,"light":20,"threshold":{"light":null,"sight":null,"sound":null,"attenuation":false}},
        {"_id":"2BB5lPRVqx4TYNvL","c":[2512,2412,3287,2412],"move":20,"sound":20,"dir":0,"door":0,"ds":0,"flags":{},"sight":20,"light":20,"threshold":{"light":null,"sight":null,"sound":null,"attenuation":false}},
        {"_id":"JLv5uk3SmMx6vCjb","c":[3287,2412,3287,2462],"move":20,"sound":20,"dir":0,"door":0,"ds":0,"flags":{},"sight":20,"light":20,"threshold":{"light":null,"sight":null,"sound":null,"attenuation":false}},
        {"_id":"wj0pUU1PhrsgQf3J","c":[1575,2587,1512,2587],"move":20,"sound":20,"dir":0,"door":0,"ds":0,"flags":{},"sight":20,"light":20,"threshold":{"light":null,"sight":null,"sound":null,"attenuation":false}},
        {"_id":"IHxF98fcWwX9Mozh","c":[1575,2587,1575,2612],"move":20,"sound":20,"dir":0,"door":0,"ds":0,"flags":{},"sight":20,"light":20,"threshold":{"light":null,"sight":null,"sound":null,"attenuation":false}},
        {"_id":"cXa61e6AEGzsXVv9","c":[1575,2587,1575,2612],"move":20,"sound":20,"dir":0,"door":0,"ds":0,"flags":{},"sight":20,"light":20,"threshold":{"light":null,"sight":null,"sound":null,"attenuation":false}},
        {"_id":"odDQRDT6Rhm0tglR","c":[1575,2700,1575,2687],"move":20,"sound":20,"dir":0,"door":0,"ds":0,"flags":{},"sight":20,"light":20,"threshold":{"light":null,"sight":null,"sound":null,"attenuation":false}},
        {"_id":"exiNnY1mf3xxvIQV","c":[1575,2612,1575,2687],"move":20,"sound":20,"dir":0,"door":1,"ds":0,"flags":{},"sight":20,"light":20,"threshold":{"light":null,"sight":null,"sound":null,"attenuation":false}}
    ],
    "lights": [
    
    ],
    "drawings": [
    
    ]
}
