{
    "walls": [
        {"_id":"2BYph5eUEySppL3C","flags":{},"c":[3137,1975,3000,1787],"move":20,"door":0,"ds":0,"sight":20,"light":20,"sound":20,"dir":0,"threshold":{"light":null,"sight":null,"sound":null,"attenuation":false}},
        {"_id":"fFxuBf538t9hbWEn","flags":{},"c":[3000,1787,3100,1375],"move":20,"door":0,"ds":0,"sight":20,"light":20,"sound":20,"dir":0,"threshold":{"light":null,"sight":null,"sound":null,"attenuation":false}},
        {"_id":"VZs69mlhZgtyiV5F","flags":{},"c":[3100,1375,3062,1150],"move":20,"door":0,"ds":0,"sight":20,"light":20,"sound":20,"dir":0,"threshold":{"light":null,"sight":null,"sound":null,"attenuation":false}},
        {"_id":"2g2sCpEMQrtjnS1x","flags":{},"c":[3062,1150,2462,1137],"move":20,"door":0,"ds":0,"sight":20,"light":20,"sound":20,"dir":0,"threshold":{"light":null,"sight":null,"sound":null,"attenuation":false}},
        {"_id":"WqFhKXJFvRjeY6Rv","flags":{},"c":[2325,1137,2325,1062],"move":20,"door":0,"ds":0,"sight":20,"light":20,"sound":20,"dir":0,"threshold":{"light":null,"sight":null,"sound":null,"attenuation":false}},
        {"_id":"L0wbt5FTyzJphBQe","flags":{},"c":[2325,1062,2462,1137],"move":20,"door":0,"ds":0,"sight":20,"light":20,"sound":20,"dir":0,"threshold":{"light":null,"sight":null,"sound":null,"attenuation":false}},
        {"_id":"DhDjgp1b6Hxxa6QO","flags":{},"c":[2325,1137,2462,1137],"move":20,"door":0,"ds":0,"sight":20,"light":20,"sound":20,"dir":0,"threshold":{"light":null,"sight":null,"sound":null,"attenuation":false}},
        {"_id":"uO5aiObTg4ccRPu7","flags":{},"c":[3062,1150,3062,800],"move":20,"door":0,"ds":0,"sight":20,"light":20,"sound":20,"dir":0,"threshold":{"light":null,"sight":null,"sound":null,"attenuation":false}},
        {"_id":"3iHLE9y3lq7ibavg","flags":{},"c":[3062,800,2575,825],"move":20,"door":0,"ds":0,"sight":20,"light":20,"sound":20,"dir":0,"threshold":{"light":null,"sight":null,"sound":null,"attenuation":false}},
        {"_id":"U0tVVfPJLQon78wW","flags":{},"c":[2575,825,2350,800],"move":20,"door":0,"ds":0,"sight":20,"light":20,"sound":20,"dir":0,"threshold":{"light":null,"sight":null,"sound":null,"attenuation":false}},
        {"_id":"pN3KAWcLkVpN2pCG","flags":{},"c":[2350,800,2187,837],"move":20,"door":0,"ds":0,"sight":20,"light":20,"sound":20,"dir":0,"threshold":{"light":null,"sight":null,"sound":null,"attenuation":false}},
        {"_id":"JHFzXzBPhowXQkct","flags":{},"c":[2187,837,1975,800],"move":20,"door":0,"ds":0,"sight":20,"light":20,"sound":20,"dir":0,"threshold":{"light":null,"sight":null,"sound":null,"attenuation":false}},
        {"_id":"74VowsQkzfk8xxXN","flags":{},"c":[1975,800,1725,887],"move":20,"door":0,"ds":0,"sight":20,"light":20,"sound":20,"dir":0,"threshold":{"light":null,"sight":null,"sound":null,"attenuation":false}},
        {"_id":"ZQkNNXe3PNtReTNp","flags":{},"c":[1725,887,1662,1050],"move":20,"door":0,"ds":0,"sight":20,"light":20,"sound":20,"dir":0,"threshold":{"light":null,"sight":null,"sound":null,"attenuation":false}},
        {"_id":"x1DRI4J4tt5nMbht","flags":{},"c":[1662,1050,1575,900],"move":20,"door":0,"ds":0,"sight":20,"light":20,"sound":20,"dir":0,"threshold":{"light":null,"sight":null,"sound":null,"attenuation":false}},
        {"_id":"V6Vx1LzCZsCrKI9p","flags":{},"c":[1575,900,1312,837],"move":20,"door":0,"ds":0,"sight":20,"light":20,"sound":20,"dir":0,"threshold":{"light":null,"sight":null,"sound":null,"attenuation":false}},
        {"_id":"MLibTtTLPBg7ipYE","flags":{},"c":[1312,837,1112,812],"move":20,"door":0,"ds":0,"sight":20,"light":20,"sound":20,"dir":0,"threshold":{"light":null,"sight":null,"sound":null,"attenuation":false}},
        {"_id":"XfCf2AaPddHZW9uF","flags":{},"c":[1112,812,862,875],"move":20,"door":0,"ds":0,"sight":20,"light":20,"sound":20,"dir":0,"threshold":{"light":null,"sight":null,"sound":null,"attenuation":false}},
        {"_id":"8JZLhyP50zPGcXDI","flags":{},"c":[862,875,750,1175],"move":20,"door":0,"ds":0,"sight":20,"light":20,"sound":20,"dir":0,"threshold":{"light":null,"sight":null,"sound":null,"attenuation":false}},
        {"_id":"FTEOiqqMrxOXu3nZ","flags":{},"c":[750,1175,712,1525],"move":20,"door":0,"ds":0,"sight":20,"light":20,"sound":20,"dir":0,"threshold":{"light":null,"sight":null,"sound":null,"attenuation":false}},
        {"_id":"RTHKZiqwIMOf2yfh","flags":{},"c":[712,1525,700,1700],"move":20,"door":0,"ds":0,"sight":20,"light":20,"sound":20,"dir":0,"threshold":{"light":null,"sight":null,"sound":null,"attenuation":false}},
        {"_id":"BYOiXOS65KrCs5hT","flags":{},"c":[700,1700,800,1962],"move":20,"door":0,"ds":0,"sight":20,"light":20,"sound":20,"dir":0,"threshold":{"light":null,"sight":null,"sound":null,"attenuation":false}},
        {"_id":"L6apArcY7m63JiFm","flags":{},"c":[800,1962,962,1962],"move":20,"door":0,"ds":0,"sight":20,"light":20,"sound":20,"dir":0,"threshold":{"light":null,"sight":null,"sound":null,"attenuation":false}},
        {"_id":"UMHG2jGHoiDS3OG0","flags":{},"c":[962,1962,1062,1887],"move":20,"door":0,"ds":0,"sight":20,"light":20,"sound":20,"dir":0,"threshold":{"light":null,"sight":null,"sound":null,"attenuation":false}},
        {"_id":"G0UwQIybdhROYzbe","flags":{},"c":[1062,1887,1200,1862],"move":20,"door":0,"ds":0,"sight":20,"light":20,"sound":20,"dir":0,"threshold":{"light":null,"sight":null,"sound":null,"attenuation":false}},
        {"_id":"CsEgSSMGwv0CwbeF","flags":{},"c":[962,1962,800,2062],"move":20,"door":0,"ds":0,"sight":20,"light":20,"sound":20,"dir":0,"threshold":{"light":null,"sight":null,"sound":null,"attenuation":false}},
        {"_id":"az4CT6IsZRIntURy","flags":{},"c":[800,2062,737,2237],"move":20,"door":0,"ds":0,"sight":20,"light":20,"sound":20,"dir":0,"threshold":{"light":null,"sight":null,"sound":null,"attenuation":false}},
        {"_id":"B3isxnOneMOlvn2I","flags":{},"c":[737,2237,712,2475],"move":20,"door":0,"ds":0,"sight":20,"light":20,"sound":20,"dir":0,"threshold":{"light":null,"sight":null,"sound":null,"attenuation":false}},
        {"_id":"xA9cde1Oqv7gXRFo","flags":{},"c":[712,2475,700,2862],"move":20,"door":0,"ds":0,"sight":20,"light":20,"sound":20,"dir":0,"threshold":{"light":null,"sight":null,"sound":null,"attenuation":false}},
        {"_id":"jUZqPJnBECZcy7ks","flags":{},"c":[700,2862,700,3712],"move":20,"door":0,"ds":0,"sight":20,"light":20,"sound":20,"dir":0,"threshold":{"light":null,"sight":null,"sound":null,"attenuation":false}},
        {"_id":"lua3px5zFqcMOfvt","flags":{},"c":[700,3712,887,3762],"move":20,"door":0,"ds":0,"sight":20,"light":20,"sound":20,"dir":0,"threshold":{"light":null,"sight":null,"sound":null,"attenuation":false}},
        {"_id":"qZBn19CxOuea02yV","flags":{},"c":[887,3762,3000,3787],"move":20,"door":0,"ds":0,"sight":20,"light":20,"sound":20,"dir":0,"threshold":{"light":null,"sight":null,"sound":null,"attenuation":false}},
        {"_id":"Rro0wFf8dfIt6YgG","flags":{},"c":[3000,3787,3025,3487],"move":20,"door":0,"ds":0,"sight":20,"light":20,"sound":20,"dir":0,"threshold":{"light":null,"sight":null,"sound":null,"attenuation":false}},
        {"_id":"tckxKTrkjYD6XRg8","flags":{},"c":[3025,3487,3025,3150],"move":20,"door":0,"ds":0,"sight":20,"light":20,"sound":20,"dir":0,"threshold":{"light":null,"sight":null,"sound":null,"attenuation":false}},
        {"_id":"IxF7BZf3R8M2KlRD","flags":{},"c":[3025,3150,3012,2687],"move":20,"door":0,"ds":0,"sight":20,"light":20,"sound":20,"dir":0,"threshold":{"light":null,"sight":null,"sound":null,"attenuation":false}},
        {"_id":"IQmBliWmIY4jCJTS","flags":{},"c":[3012,2687,2862,2375],"move":20,"door":0,"ds":0,"sight":20,"light":20,"sound":20,"dir":0,"threshold":{"light":null,"sight":null,"sound":null,"attenuation":false}},
        {"_id":"6WEXlzaBYFjnWjwt","flags":{},"c":[2862,2375,2837,2250],"move":20,"door":0,"ds":0,"sight":20,"light":20,"sound":20,"dir":0,"threshold":{"light":null,"sight":null,"sound":null,"attenuation":false}},
        {"_id":"3TzQujTUvBdhoFVV","flags":{},"c":[2837,2250,3200,2250],"move":20,"door":0,"ds":0,"sight":20,"light":20,"sound":20,"dir":0,"threshold":{"light":null,"sight":null,"sound":null,"attenuation":false}},
        {"_id":"l6rzr6a3ADJmVe3i","flags":{},"c":[3200,2250,3200,1975],"move":20,"door":0,"ds":0,"sight":20,"light":20,"sound":20,"dir":0,"threshold":{"light":null,"sight":null,"sound":null,"attenuation":false}},
        {"_id":"rRQN0htje5WryTHN","flags":{},"c":[3200,1975,3137,1975],"move":20,"door":0,"ds":0,"sight":20,"light":20,"sound":20,"dir":0,"threshold":{"light":null,"sight":null,"sound":null,"attenuation":false}},
        {"_id":"Mwg2OTFHkcT8GmWh","flags":{},"c":[2025,1075,1937,1362],"move":20,"door":0,"ds":0,"sight":20,"light":20,"sound":20,"dir":0,"threshold":{"light":null,"sight":null,"sound":null,"attenuation":false}},
        {"_id":"VY90aFFYuxdokqt3","flags":{},"c":[1937,1362,1812,1412],"move":20,"door":0,"ds":0,"sight":20,"light":20,"sound":20,"dir":0,"threshold":{"light":null,"sight":null,"sound":null,"attenuation":false}},
        {"_id":"aidayE9uSGB6lMsD","flags":{},"c":[1812,1412,1612,1362],"move":20,"door":0,"ds":0,"sight":20,"light":20,"sound":20,"dir":0,"threshold":{"light":null,"sight":null,"sound":null,"attenuation":false}},
        {"_id":"BEUg2knVygjX4jcW","flags":{},"c":[1612,1362,1637,1562],"move":20,"door":0,"ds":0,"sight":20,"light":20,"sound":20,"dir":0,"threshold":{"light":null,"sight":null,"sound":null,"attenuation":false}},
        {"_id":"vkTXuNZVoanrWYkf","flags":{},"c":[1637,1562,1812,1412],"move":20,"door":0,"ds":0,"sight":20,"light":20,"sound":20,"dir":0,"threshold":{"light":null,"sight":null,"sound":null,"attenuation":false}},
        {"_id":"Ix8Pcxtq30N5o8R9","flags":{},"c":[1637,1562,1650,1900],"move":20,"door":0,"ds":0,"sight":20,"light":20,"sound":20,"dir":0,"threshold":{"light":null,"sight":null,"sound":null,"attenuation":false}},
        {"_id":"kQqj39kSgyG4JaFL","flags":{},"c":[1650,1900,1712,1987],"move":20,"door":0,"ds":0,"sight":20,"light":20,"sound":20,"dir":0,"threshold":{"light":null,"sight":null,"sound":null,"attenuation":false}},
        {"_id":"y1oS3c74Un7DjtXT","flags":{},"c":[1712,1987,1875,2100],"move":20,"door":0,"ds":0,"sight":20,"light":20,"sound":20,"dir":0,"threshold":{"light":null,"sight":null,"sound":null,"attenuation":false}},
        {"_id":"H7Tiu8nWxErZyRCq","flags":{},"c":[1875,2100,1962,2325],"move":20,"door":0,"ds":0,"sight":20,"light":20,"sound":20,"dir":0,"threshold":{"light":null,"sight":null,"sound":null,"attenuation":false}},
        {"_id":"JUsvGepIWclQuuBg","flags":{},"c":[1962,2325,1825,2350],"move":20,"door":0,"ds":0,"sight":20,"light":20,"sound":20,"dir":0,"threshold":{"light":null,"sight":null,"sound":null,"attenuation":false}},
        {"_id":"LI81bVQKaj5Ds2Ae","flags":{},"c":[1825,2350,1875,2100],"move":20,"door":0,"ds":0,"sight":20,"light":20,"sound":20,"dir":0,"threshold":{"light":null,"sight":null,"sound":null,"attenuation":false}},
        {"_id":"gOnovYYhLwMqc5y5","flags":{},"c":[1825,2350,1675,2437],"move":20,"door":0,"ds":0,"sight":20,"light":20,"sound":20,"dir":0,"threshold":{"light":null,"sight":null,"sound":null,"attenuation":false}},
        {"_id":"R4EeZZ2OGKRHKJUb","flags":{},"c":[1675,2437,1525,2450],"move":20,"door":0,"ds":0,"sight":20,"light":20,"sound":20,"dir":0,"threshold":{"light":null,"sight":null,"sound":null,"attenuation":false}},
        {"_id":"6ecYhRElmdaSMIsM","flags":{},"c":[1525,2450,1462,2162],"move":20,"door":0,"ds":0,"sight":20,"light":20,"sound":20,"dir":0,"threshold":{"light":null,"sight":null,"sound":null,"attenuation":false}},
        {"_id":"pYplT1NUKcRTApt0","flags":{},"c":[1462,2162,1375,2300],"move":20,"door":0,"ds":0,"sight":20,"light":20,"sound":20,"dir":0,"threshold":{"light":null,"sight":null,"sound":null,"attenuation":false}},
        {"_id":"kOWChhKDjipDwruf","flags":{},"c":[1375,2300,1450,2525],"move":20,"door":0,"ds":0,"sight":20,"light":20,"sound":20,"dir":0,"threshold":{"light":null,"sight":null,"sound":null,"attenuation":false}},
        {"_id":"1ZJyjEtnWJ13uYnU","flags":{},"c":[1450,2525,1562,2500],"move":20,"door":0,"ds":0,"sight":20,"light":20,"sound":20,"dir":0,"threshold":{"light":null,"sight":null,"sound":null,"attenuation":false}},
        {"_id":"hI0R5oAPfPELNotL","flags":{},"c":[1562,2500,1675,2437],"move":20,"door":0,"ds":0,"sight":20,"light":20,"sound":20,"dir":0,"threshold":{"light":null,"sight":null,"sound":null,"attenuation":false}},
        {"_id":"XEqa4FRtqjguNuaK","flags":{},"c":[1212,2850,1175,2762],"move":20,"door":0,"ds":0,"sight":20,"light":20,"sound":20,"dir":0,"threshold":{"light":null,"sight":null,"sound":null,"attenuation":false}},
        {"_id":"MJp2XxxVdHyEghN3","flags":{},"c":[1175,2762,1037,2875],"move":20,"door":0,"ds":0,"sight":20,"light":20,"sound":20,"dir":0,"threshold":{"light":null,"sight":null,"sound":null,"attenuation":false}},
        {"_id":"pWZz3fie8czza45s","flags":{},"c":[1037,2875,1000,3000],"move":20,"door":0,"ds":0,"sight":20,"light":20,"sound":20,"dir":0,"threshold":{"light":null,"sight":null,"sound":null,"attenuation":false}},
        {"_id":"8Pn9xVE3alPxtQIx","flags":{},"c":[1212,2850,1037,2875],"move":20,"door":0,"ds":0,"sight":20,"light":20,"sound":20,"dir":0,"threshold":{"light":null,"sight":null,"sound":null,"attenuation":false}},
        {"_id":"ErTYmcbJBMcRRgEt","flags":{},"c":[1000,3000,1312,3287],"move":20,"door":0,"ds":0,"sight":20,"light":20,"sound":20,"dir":0,"threshold":{"light":null,"sight":null,"sound":null,"attenuation":false}},
        {"_id":"lZkdxx2ILA8arC5X","flags":{},"c":[1312,3287,1100,3500],"move":20,"door":0,"ds":0,"sight":20,"light":20,"sound":20,"dir":0,"threshold":{"light":null,"sight":null,"sound":null,"attenuation":false}},
        {"_id":"kYFaHIsWL0PFnC6A","flags":{},"c":[1312,3287,1675,3300],"move":20,"door":0,"ds":0,"sight":20,"light":20,"sound":20,"dir":0,"threshold":{"light":null,"sight":null,"sound":null,"attenuation":false}},
        {"_id":"ZdHNvP3EZyaLRiUj","flags":{},"c":[1675,3300,1812,3262],"move":20,"door":0,"ds":0,"sight":20,"light":20,"sound":20,"dir":0,"threshold":{"light":null,"sight":null,"sound":null,"attenuation":false}},
        {"_id":"ac94YcAz47SsuSVX","flags":{},"c":[1812,3262,1862,3387],"move":20,"door":0,"ds":0,"sight":20,"light":20,"sound":20,"dir":0,"threshold":{"light":null,"sight":null,"sound":null,"attenuation":false}},
        {"_id":"q2IHd88TRNJxfy4b","flags":{},"c":[1862,3387,1962,3487],"move":20,"door":0,"ds":0,"sight":20,"light":20,"sound":20,"dir":0,"threshold":{"light":null,"sight":null,"sound":null,"attenuation":false}},
        {"_id":"RBaMQK4l1WQxte15","flags":{},"c":[1962,3487,1887,3525],"move":20,"door":0,"ds":0,"sight":20,"light":20,"sound":20,"dir":0,"threshold":{"light":null,"sight":null,"sound":null,"attenuation":false}},
        {"_id":"u9wcil1sCF7UxozX","flags":{},"c":[1887,3525,1887,3512],"move":20,"door":0,"ds":0,"sight":20,"light":20,"sound":20,"dir":0,"threshold":{"light":null,"sight":null,"sound":null,"attenuation":false}},
        {"_id":"3dE7uqNkBdLmVOk6","flags":{},"c":[1887,3512,1737,3400],"move":20,"door":0,"ds":0,"sight":20,"light":20,"sound":20,"dir":0,"threshold":{"light":null,"sight":null,"sound":null,"attenuation":false}},
        {"_id":"sWlQEG79RwhmjQpU","flags":{},"c":[1737,3400,1675,3300],"move":20,"door":0,"ds":0,"sight":20,"light":20,"sound":20,"dir":0,"threshold":{"light":null,"sight":null,"sound":null,"attenuation":false}},
        {"_id":"1UtzPzobK3VzTOm7","flags":{},"c":[2325,3512,2562,3387],"move":20,"door":0,"ds":0,"sight":20,"light":20,"sound":20,"dir":0,"threshold":{"light":null,"sight":null,"sound":null,"attenuation":false}},
        {"_id":"ENTqTKHO2U6R616c","flags":{},"c":[2787,3275,2812,3187],"move":20,"door":0,"ds":0,"sight":20,"light":20,"sound":20,"dir":0,"threshold":{"light":null,"sight":null,"sound":null,"attenuation":false}},
        {"_id":"9l691nOHeFO4p2TQ","flags":{},"c":[2787,3275,2837,3337],"move":20,"door":0,"ds":0,"sight":20,"light":20,"sound":20,"dir":0,"threshold":{"light":null,"sight":null,"sound":null,"attenuation":false}},
        {"_id":"BM5agvAws6y2IJy0","flags":{},"c":[2325,3512,2375,3362],"move":20,"door":0,"ds":0,"sight":20,"light":20,"sound":20,"dir":0,"threshold":{"light":null,"sight":null,"sound":null,"attenuation":false}},
        {"_id":"VrDPrBnutsUf7aNw","flags":{},"c":[2375,3362,2462,3325],"move":20,"door":0,"ds":0,"sight":20,"light":20,"sound":20,"dir":0,"threshold":{"light":null,"sight":null,"sound":null,"attenuation":false}},
        {"_id":"q6FsMbdPfi0z0dLa","flags":{},"c":[2462,3325,2562,3387],"move":20,"door":0,"ds":0,"sight":20,"light":20,"sound":20,"dir":0,"threshold":{"light":null,"sight":null,"sound":null,"attenuation":false}},
        {"_id":"VIQiphzP5AI4GOpr","flags":{},"c":[2562,3387,2787,3275],"move":20,"door":0,"ds":0,"sight":20,"light":20,"sound":20,"dir":0,"threshold":{"light":null,"sight":null,"sound":null,"attenuation":false}},
        {"_id":"FYKjunnmoEYwMcXA","flags":{},"c":[2375,3362,2250,3300],"move":20,"door":0,"ds":0,"sight":20,"light":20,"sound":20,"dir":0,"threshold":{"light":null,"sight":null,"sound":null,"attenuation":false}},
        {"_id":"cBGDdKvyLyD4dLwj","flags":{},"c":[2250,3300,2175,3162],"move":20,"door":0,"ds":0,"sight":20,"light":20,"sound":20,"dir":0,"threshold":{"light":null,"sight":null,"sound":null,"attenuation":false}},
        {"_id":"Xo0T97ADqgkQbc8B","flags":{},"c":[2175,3162,2125,2975],"move":20,"door":0,"ds":0,"sight":20,"light":20,"sound":20,"dir":0,"threshold":{"light":null,"sight":null,"sound":null,"attenuation":false}},
        {"_id":"LCn0HM8a68oYuVx9","flags":{},"c":[2125,2975,2037,2950],"move":20,"door":0,"ds":0,"sight":20,"light":20,"sound":20,"dir":0,"threshold":{"light":null,"sight":null,"sound":null,"attenuation":false}},
        {"_id":"vfV3BRvsWOqIxCfJ","flags":{},"c":[2037,2950,2175,3162],"move":20,"door":0,"ds":0,"sight":20,"light":20,"sound":20,"dir":0,"threshold":{"light":null,"sight":null,"sound":null,"attenuation":false}},
        {"_id":"A7kxex1cZJKhzgq9","flags":{},"c":[2162,2550,2200,2762],"move":20,"door":0,"ds":0,"sight":20,"light":20,"sound":20,"dir":0,"threshold":{"light":null,"sight":null,"sound":null,"attenuation":false}},
        {"_id":"mMm6vmD3IGrwawoz","flags":{},"c":[2200,2762,2425,2800],"move":20,"door":0,"ds":0,"sight":20,"light":20,"sound":20,"dir":0,"threshold":{"light":null,"sight":null,"sound":null,"attenuation":false}},
        {"_id":"LTzJwtXCMKwqCJeG","flags":{},"c":[2425,2800,2662,2762],"move":20,"door":0,"ds":0,"sight":20,"light":20,"sound":20,"dir":0,"threshold":{"light":null,"sight":null,"sound":null,"attenuation":false}},
        {"_id":"R7oUYiDorkWSxh4Z","flags":{},"c":[2662,2762,2612,2500],"move":20,"door":0,"ds":0,"sight":20,"light":20,"sound":20,"dir":0,"threshold":{"light":null,"sight":null,"sound":null,"attenuation":false}},
        {"_id":"GAuqimdZEDrGfQNF","flags":{},"c":[2612,2500,2437,2400],"move":20,"door":0,"ds":0,"sight":20,"light":20,"sound":20,"dir":0,"threshold":{"light":null,"sight":null,"sound":null,"attenuation":false}},
        {"_id":"fatgWHXnWgSechfB","flags":{},"c":[2437,2400,2250,2537],"move":20,"door":0,"ds":0,"sight":20,"light":20,"sound":20,"dir":0,"threshold":{"light":null,"sight":null,"sound":null,"attenuation":false}},
        {"_id":"uzdlxQi7aRVOv3S9","flags":{},"c":[2250,2537,2162,2550],"move":20,"door":0,"ds":0,"sight":20,"light":20,"sound":20,"dir":0,"threshold":{"light":null,"sight":null,"sound":null,"attenuation":false}},
        {"_id":"6SFdIiEn5gDi2q7T","flags":{},"c":[2337,1487,2262,1625],"move":20,"door":0,"ds":0,"sight":20,"light":20,"sound":20,"dir":0,"threshold":{"light":null,"sight":null,"sound":null,"attenuation":false}},
        {"_id":"OsfUba4tudfo4dTC","flags":{},"c":[2262,1625,2275,1800],"move":20,"door":0,"ds":0,"sight":20,"light":20,"sound":20,"dir":0,"threshold":{"light":null,"sight":null,"sound":null,"attenuation":false}},
        {"_id":"1woLsDzddSn1zFVc","flags":{},"c":[2275,1800,2225,1987],"move":20,"door":0,"ds":0,"sight":20,"light":20,"sound":20,"dir":0,"threshold":{"light":null,"sight":null,"sound":null,"attenuation":false}},
        {"_id":"0swhjYZVfgmQgOpa","flags":{},"c":[2225,1987,2275,2162],"move":20,"door":0,"ds":0,"sight":20,"light":20,"sound":20,"dir":0,"threshold":{"light":null,"sight":null,"sound":null,"attenuation":false}},
        {"_id":"GiT4TByOf4KffIzx","flags":{},"c":[2275,2162,2612,2037],"move":20,"door":0,"ds":0,"sight":20,"light":20,"sound":20,"dir":0,"threshold":{"light":null,"sight":null,"sound":null,"attenuation":false}},
        {"_id":"3GsFGoIRgFVdG9aC","flags":{},"c":[2612,2037,2537,1887],"move":20,"door":0,"ds":0,"sight":20,"light":20,"sound":20,"dir":0,"threshold":{"light":null,"sight":null,"sound":null,"attenuation":false}},
        {"_id":"jOC7GOzzCgkRhmZa","flags":{},"c":[2537,1887,2362,1787],"move":20,"door":0,"ds":0,"sight":20,"light":20,"sound":20,"dir":0,"threshold":{"light":null,"sight":null,"sound":null,"attenuation":false}},
        {"_id":"WO9yotnc9LGu6x7N","flags":{},"c":[2362,1787,2325,1612],"move":20,"door":0,"ds":0,"sight":20,"light":20,"sound":20,"dir":0,"threshold":{"light":null,"sight":null,"sound":null,"attenuation":false}},
        {"_id":"o1dDlSutaSrSF06W","flags":{},"c":[2325,1612,2337,1487],"move":20,"door":0,"ds":0,"sight":20,"light":20,"sound":20,"dir":0,"threshold":{"light":null,"sight":null,"sound":null,"attenuation":false}}
    ],
    "lights": [
    
    ],
    "drawings": [
    
    ]
}
