{
    "walls": [
        {"_id":"lK4OQ8eT0SPt769h","flags":{},"c":[500,1400,1100,1400],"move":20,"door":0,"ds":0,"sight":20,"light":20,"sound":20,"dir":0,"threshold":{"light":null,"sight":null,"sound":null,"attenuation":false}},
        {"_id":"vIR8498mjJ7xIfbk","flags":{},"c":[1100,1400,1100,1200],"move":20,"door":0,"ds":0,"sight":20,"light":20,"sound":20,"dir":0,"threshold":{"light":null,"sight":null,"sound":null,"attenuation":false}},
        {"_id":"eC8KUmyQNzIIQSCU","flags":{},"c":[1100,1200,500,1200],"move":20,"door":0,"ds":0,"sight":20,"light":20,"sound":20,"dir":0,"threshold":{"light":null,"sight":null,"sound":null,"attenuation":false}},
        {"_id":"TNlBlWYnrKk9YojG","flags":{},"c":[500,1200,500,600],"move":20,"door":0,"ds":0,"sight":20,"light":20,"sound":20,"dir":0,"threshold":{"light":null,"sight":null,"sound":null,"attenuation":false}},
        {"_id":"rnqxBc1KM23QYB0U","flags":{},"c":[500,600,1100,600],"move":20,"door":0,"ds":0,"sight":20,"light":20,"sound":20,"dir":0,"threshold":{"light":null,"sight":null,"sound":null,"attenuation":false}},
        {"_id":"LmjfVuLv8Y5k6YP4","flags":{},"c":[1100,600,1100,800],"move":20,"door":0,"ds":0,"sight":20,"light":20,"sound":20,"dir":0,"threshold":{"light":null,"sight":null,"sound":null,"attenuation":false}},
        {"_id":"MPQNDtmSqeZLrUiK","flags":{},"c":[1100,800,1700,800],"move":20,"door":0,"ds":0,"sight":20,"light":20,"sound":20,"dir":0,"threshold":{"light":null,"sight":null,"sound":null,"attenuation":false}},
        {"_id":"20KQ7Qa0NLx3AcP0","flags":{},"c":[1700,800,1700,600],"move":20,"door":0,"ds":0,"sight":20,"light":20,"sound":20,"dir":0,"threshold":{"light":null,"sight":null,"sound":null,"attenuation":false}},
        {"_id":"9vCImWDvPwwBJ9Xq","flags":{},"c":[1700,600,2300,600],"move":20,"door":0,"ds":0,"sight":20,"light":20,"sound":20,"dir":0,"threshold":{"light":null,"sight":null,"sound":null,"attenuation":false}},
        {"_id":"d0aUiXZzw3EAi9gh","flags":{},"c":[2300,600,2300,1200],"move":20,"door":0,"ds":0,"sight":20,"light":20,"sound":20,"dir":0,"threshold":{"light":null,"sight":null,"sound":null,"attenuation":false}},
        {"_id":"qeqtCUIuw6iAygkt","flags":{},"c":[2300,1200,1700,1200],"move":20,"door":0,"ds":0,"sight":20,"light":20,"sound":20,"dir":0,"threshold":{"light":null,"sight":null,"sound":null,"attenuation":false}},
        {"_id":"pjSj9r12MmaRz3uD","flags":{},"c":[1700,1200,1700,1400],"move":20,"door":0,"ds":0,"sight":20,"light":20,"sound":20,"dir":0,"threshold":{"light":null,"sight":null,"sound":null,"attenuation":false}},
        {"_id":"Ugu7UZgUXfz1pUzb","flags":{},"c":[1700,1400,2300,1400],"move":20,"door":0,"ds":0,"sight":20,"light":20,"sound":20,"dir":0,"threshold":{"light":null,"sight":null,"sound":null,"attenuation":false}},
        {"_id":"Y6L20SJYhCRoA5tF","flags":{},"c":[2300,1400,2300,1600],"move":20,"door":0,"ds":0,"sight":20,"light":20,"sound":20,"dir":0,"threshold":{"light":null,"sight":null,"sound":null,"attenuation":false}},
        {"_id":"1kBQyo5wVgw9xK2J","flags":{},"c":[2300,1600,1700,1600],"move":20,"door":0,"ds":0,"sight":20,"light":20,"sound":20,"dir":0,"threshold":{"light":null,"sight":null,"sound":null,"attenuation":false}},
        {"_id":"pPouFX8kaTJy9cS9","flags":{},"c":[1700,1600,1700,2400],"move":20,"door":0,"ds":0,"sight":20,"light":20,"sound":20,"dir":0,"threshold":{"light":null,"sight":null,"sound":null,"attenuation":false}},
        {"_id":"z4aqKaaToNnW53sr","flags":{},"c":[1700,2400,2300,2400],"move":20,"door":0,"ds":0,"sight":20,"light":20,"sound":20,"dir":0,"threshold":{"light":null,"sight":null,"sound":null,"attenuation":false}},
        {"_id":"7Y7Mg3Dn8Hluzrq8","flags":{},"c":[2300,2400,2300,3000],"move":20,"door":0,"ds":0,"sight":20,"light":20,"sound":20,"dir":0,"threshold":{"light":null,"sight":null,"sound":null,"attenuation":false}},
        {"_id":"5PT2nKiexCQj5NrM","flags":{},"c":[2300,3000,1700,3000],"move":20,"door":0,"ds":0,"sight":20,"light":20,"sound":20,"dir":0,"threshold":{"light":null,"sight":null,"sound":null,"attenuation":false}},
        {"_id":"U9BtMXxgBT527dYz","flags":{},"c":[1700,3000,1700,2800],"move":20,"door":0,"ds":0,"sight":20,"light":20,"sound":20,"dir":0,"threshold":{"light":null,"sight":null,"sound":null,"attenuation":false}},
        {"_id":"Wux0vHgQpZFG5tP2","flags":{},"c":[1700,2800,1100,2800],"move":20,"door":0,"ds":0,"sight":20,"light":20,"sound":20,"dir":0,"threshold":{"light":null,"sight":null,"sound":null,"attenuation":false}},
        {"_id":"OIArCu94Xv93Dy3Q","flags":{},"c":[1100,2800,1100,3000],"move":20,"door":0,"ds":0,"sight":20,"light":20,"sound":20,"dir":0,"threshold":{"light":null,"sight":null,"sound":null,"attenuation":false}},
        {"_id":"Ae9pZwqk4isxHCCZ","flags":{},"c":[1100,3000,500,3000],"move":20,"door":0,"ds":0,"sight":20,"light":20,"sound":20,"dir":0,"threshold":{"light":null,"sight":null,"sound":null,"attenuation":false}},
        {"_id":"aG44xSdMQlI3lOfH","flags":{},"c":[500,3000,500,2400],"move":20,"door":0,"ds":0,"sight":20,"light":20,"sound":20,"dir":0,"threshold":{"light":null,"sight":null,"sound":null,"attenuation":false}},
        {"_id":"0pwJ5BGRf10Zw96Y","flags":{},"c":[500,2400,1100,2400],"move":20,"door":0,"ds":0,"sight":20,"light":20,"sound":20,"dir":0,"threshold":{"light":null,"sight":null,"sound":null,"attenuation":false}},
        {"_id":"6c5JRyhuOSeDzC2S","flags":{},"c":[1100,2400,1100,2200],"move":20,"door":0,"ds":0,"sight":20,"light":20,"sound":20,"dir":0,"threshold":{"light":null,"sight":null,"sound":null,"attenuation":false}},
        {"_id":"H8Gmcx0HLJEehsJ0","flags":{},"c":[1100,2200,500,2200],"move":20,"door":0,"ds":0,"sight":20,"light":20,"sound":20,"dir":0,"threshold":{"light":null,"sight":null,"sound":null,"attenuation":false}},
        {"_id":"yoa3a4NKWpmM40iR","flags":{},"c":[500,2200,500,1400],"move":20,"door":0,"ds":0,"sight":20,"light":20,"sound":20,"dir":0,"threshold":{"light":null,"sight":null,"sound":null,"attenuation":false}},
        {"_id":"hv7NOUIcqAGlAE0b","flags":{},"c":[1100,1000,1100,1200],"move":20,"door":0,"ds":0,"sight":20,"light":20,"sound":20,"dir":0,"threshold":{"light":null,"sight":null,"sound":null,"attenuation":false}},
        {"_id":"6QrJ442PKYInKLCL","flags":{},"c":[1100,1200,1300,1200],"move":20,"door":0,"ds":0,"sight":20,"light":20,"sound":20,"dir":0,"threshold":{"light":null,"sight":null,"sound":null,"attenuation":false}},
        {"_id":"F5YGwFIEHxuG29G2","flags":{},"c":[1300,1200,1300,1000],"move":20,"door":0,"ds":0,"sight":20,"light":20,"sound":20,"dir":0,"threshold":{"light":null,"sight":null,"sound":null,"attenuation":false}},
        {"_id":"P1l3HPoLhwtE8ayE","flags":{},"c":[1300,1000,1100,1000],"move":20,"door":0,"ds":0,"sight":20,"light":20,"sound":20,"dir":0,"threshold":{"light":null,"sight":null,"sound":null,"attenuation":false}},
        {"_id":"IdV2ALtyeiwl4x1H","flags":{},"c":[800,1100,900,1100],"move":20,"door":0,"ds":0,"sight":20,"light":20,"sound":20,"dir":0,"threshold":{"light":null,"sight":null,"sound":null,"attenuation":false}},
        {"_id":"dHaLRm3hSE5Zascu","flags":{},"c":[900,1100,900,1000],"move":20,"door":0,"ds":0,"sight":20,"light":20,"sound":20,"dir":0,"threshold":{"light":null,"sight":null,"sound":null,"attenuation":false}},
        {"_id":"zVtAageTfWCapy24","flags":{},"c":[900,1000,1000,1000],"move":20,"door":0,"ds":0,"sight":20,"light":20,"sound":20,"dir":0,"threshold":{"light":null,"sight":null,"sound":null,"attenuation":false}},
        {"_id":"sgbWH1wcQpMwrMdX","flags":{},"c":[1000,1000,1000,900],"move":20,"door":0,"ds":0,"sight":20,"light":20,"sound":20,"dir":0,"threshold":{"light":null,"sight":null,"sound":null,"attenuation":false}},
        {"_id":"EpHS0xEzqMSU1aLg","flags":{},"c":[1000,900,800,900],"move":20,"door":0,"ds":0,"sight":20,"light":20,"sound":20,"dir":0,"threshold":{"light":null,"sight":null,"sound":null,"attenuation":false}},
        {"_id":"eQuKwhIcTIoVVAN6","flags":{},"c":[800,900,800,1100],"move":20,"door":0,"ds":0,"sight":20,"light":20,"sound":20,"dir":0,"threshold":{"light":null,"sight":null,"sound":null,"attenuation":false}},
        {"_id":"jjbW7T8VjaoIlEzO","flags":{},"c":[1800,900,1800,1000],"move":20,"door":0,"ds":0,"sight":20,"light":20,"sound":20,"dir":0,"threshold":{"light":null,"sight":null,"sound":null,"attenuation":false}},
        {"_id":"NZqx2RZn2p2PqAs2","flags":{},"c":[1800,1000,1900,1000],"move":20,"door":0,"ds":0,"sight":20,"light":20,"sound":20,"dir":0,"threshold":{"light":null,"sight":null,"sound":null,"attenuation":false}},
        {"_id":"xS6bkdoQpXOBjvjf","flags":{},"c":[1900,1000,1900,1100],"move":20,"door":0,"ds":0,"sight":20,"light":20,"sound":20,"dir":0,"threshold":{"light":null,"sight":null,"sound":null,"attenuation":false}},
        {"_id":"TDAfMaNaEorwvElN","flags":{},"c":[1900,1100,2000,1100],"move":20,"door":0,"ds":0,"sight":20,"light":20,"sound":20,"dir":0,"threshold":{"light":null,"sight":null,"sound":null,"attenuation":false}},
        {"_id":"iZOCUTjI868CwIXy","flags":{},"c":[2000,1100,2000,900],"move":20,"door":0,"ds":0,"sight":20,"light":20,"sound":20,"dir":0,"threshold":{"light":null,"sight":null,"sound":null,"attenuation":false}},
        {"_id":"IkaPhAbP5nfNZvAH","flags":{},"c":[2000,900,1800,900],"move":20,"door":0,"ds":0,"sight":20,"light":20,"sound":20,"dir":0,"threshold":{"light":null,"sight":null,"sound":null,"attenuation":false}},
        {"_id":"o5wDkCLyYqGgSDKx","flags":{},"c":[1500,1000,1500,1200],"move":20,"door":0,"ds":0,"sight":20,"light":20,"sound":20,"dir":0,"threshold":{"light":null,"sight":null,"sound":null,"attenuation":false}},
        {"_id":"5uvtiTbN2EEDXehq","flags":{},"c":[1500,1200,1700,1200],"move":20,"door":0,"ds":0,"sight":20,"light":20,"sound":20,"dir":0,"threshold":{"light":null,"sight":null,"sound":null,"attenuation":false}},
        {"_id":"bsV7E3fY8HYPAPEu","flags":{},"c":[1700,1200,1700,1000],"move":20,"door":0,"ds":0,"sight":20,"light":20,"sound":20,"dir":0,"threshold":{"light":null,"sight":null,"sound":null,"attenuation":false}},
        {"_id":"EMwV20X5qy0ebAhi","flags":{},"c":[1700,1000,1500,1000],"move":20,"door":0,"ds":0,"sight":20,"light":20,"sound":20,"dir":0,"threshold":{"light":null,"sight":null,"sound":null,"attenuation":false}},
        {"_id":"vIVZecOLjdLD1mbp","flags":{},"c":[800,2500,800,2700],"move":20,"door":0,"ds":0,"sight":20,"light":20,"sound":20,"dir":0,"threshold":{"light":null,"sight":null,"sound":null,"attenuation":false}},
        {"_id":"mI1XYJXEumxlDkp5","flags":{},"c":[800,2700,1000,2700],"move":20,"door":0,"ds":0,"sight":20,"light":20,"sound":20,"dir":0,"threshold":{"light":null,"sight":null,"sound":null,"attenuation":false}},
        {"_id":"wTJUAkzbglnjhN07","flags":{},"c":[1000,2700,1000,2600],"move":20,"door":0,"ds":0,"sight":20,"light":20,"sound":20,"dir":0,"threshold":{"light":null,"sight":null,"sound":null,"attenuation":false}},
        {"_id":"7eln9dIVsQZt2qu2","flags":{},"c":[1000,2600,900,2600],"move":20,"door":0,"ds":0,"sight":20,"light":20,"sound":20,"dir":0,"threshold":{"light":null,"sight":null,"sound":null,"attenuation":false}},
        {"_id":"1ex16w3IHksEehIm","flags":{},"c":[900,2600,900,2500],"move":20,"door":0,"ds":0,"sight":20,"light":20,"sound":20,"dir":0,"threshold":{"light":null,"sight":null,"sound":null,"attenuation":false}},
        {"_id":"Ugjw5L1vG3S1KiSD","flags":{},"c":[900,2500,800,2500],"move":20,"door":0,"ds":0,"sight":20,"light":20,"sound":20,"dir":0,"threshold":{"light":null,"sight":null,"sound":null,"attenuation":false}},
        {"_id":"fKhNOM3qSV66DiAk","flags":{},"c":[1100,2400,1100,2600],"move":20,"door":0,"ds":0,"sight":20,"light":20,"sound":20,"dir":0,"threshold":{"light":null,"sight":null,"sound":null,"attenuation":false}},
        {"_id":"L3x6Cugn8IcbyKtW","flags":{},"c":[1100,2600,1300,2600],"move":20,"door":0,"ds":0,"sight":20,"light":20,"sound":20,"dir":0,"threshold":{"light":null,"sight":null,"sound":null,"attenuation":false}},
        {"_id":"sYT4WXTH3IcX0Jxn","flags":{},"c":[1300,2600,1300,2400],"move":20,"door":0,"ds":0,"sight":20,"light":20,"sound":20,"dir":0,"threshold":{"light":null,"sight":null,"sound":null,"attenuation":false}},
        {"_id":"GaZlCtpGGKeJ0sSm","flags":{},"c":[1300,2400,1100,2400],"move":20,"door":0,"ds":0,"sight":20,"light":20,"sound":20,"dir":0,"threshold":{"light":null,"sight":null,"sound":null,"attenuation":false}},
        {"_id":"PB0x2bpJ4Fa12EKL","flags":{},"c":[1500,2400,1500,2600],"move":20,"door":0,"ds":0,"sight":20,"light":20,"sound":20,"dir":0,"threshold":{"light":null,"sight":null,"sound":null,"attenuation":false}},
        {"_id":"ULFCgVFrHHZdDNks","flags":{},"c":[1500,2600,1700,2600],"move":20,"door":0,"ds":0,"sight":20,"light":20,"sound":20,"dir":0,"threshold":{"light":null,"sight":null,"sound":null,"attenuation":false}},
        {"_id":"Eiz87wvy78SemMzg","flags":{},"c":[1700,2600,1700,2400],"move":20,"door":0,"ds":0,"sight":20,"light":20,"sound":20,"dir":0,"threshold":{"light":null,"sight":null,"sound":null,"attenuation":false}},
        {"_id":"2TKfL3oJ1oKBATb2","flags":{},"c":[1700,2400,1500,2400],"move":20,"door":0,"ds":0,"sight":20,"light":20,"sound":20,"dir":0,"threshold":{"light":null,"sight":null,"sound":null,"attenuation":false}},
        {"_id":"wmEhMuFDGtJSVXoT","flags":{},"c":[1800,2600,1800,2700],"move":20,"door":0,"ds":0,"sight":20,"light":20,"sound":20,"dir":0,"threshold":{"light":null,"sight":null,"sound":null,"attenuation":false}},
        {"_id":"ejgAdhI9JjgmD8wI","flags":{},"c":[1800,2700,2000,2700],"move":20,"door":0,"ds":0,"sight":20,"light":20,"sound":20,"dir":0,"threshold":{"light":null,"sight":null,"sound":null,"attenuation":false}},
        {"_id":"Yp2Uu2kQqPAwHRcu","flags":{},"c":[2000,2700,2000,2500],"move":20,"door":0,"ds":0,"sight":20,"light":20,"sound":20,"dir":0,"threshold":{"light":null,"sight":null,"sound":null,"attenuation":false}},
        {"_id":"Vxg28r6WbQ3j7xdz","flags":{},"c":[2000,2500,1900,2500],"move":20,"door":0,"ds":0,"sight":20,"light":20,"sound":20,"dir":0,"threshold":{"light":null,"sight":null,"sound":null,"attenuation":false}},
        {"_id":"HOaF7Uwnj73If9CM","flags":{},"c":[1900,2500,1900,2600],"move":20,"door":0,"ds":0,"sight":20,"light":20,"sound":20,"dir":0,"threshold":{"light":null,"sight":null,"sound":null,"attenuation":false}},
        {"_id":"GkX2IWXrraTVIeVV","flags":{},"c":[1900,2600,1800,2600],"move":20,"door":0,"ds":0,"sight":20,"light":20,"sound":20,"dir":0,"threshold":{"light":null,"sight":null,"sound":null,"attenuation":false}}
    ],
    "lights": [
    
    ],
    "drawings": [
    
    ]
}
