{
    "walls": [
        {"_id":"pCAD0wlUcD2Dj0lg","flags":{},"c":[1400,1937,1612,1912],"move":20,"door":0,"ds":0,"sight":20,"light":20,"sound":20,"dir":0,"threshold":{"light":null,"sight":null,"sound":null,"attenuation":false}},
        {"_id":"VXPIFp3OMllxw6ds","flags":{},"c":[1712,1862,1912,1700],"move":20,"door":0,"ds":0,"sight":20,"light":20,"sound":20,"dir":0,"threshold":{"light":null,"sight":null,"sound":null,"attenuation":false}},
        {"_id":"QlytR1IrKSeJl3j5","flags":{},"c":[1912,1700,2037,1462],"move":20,"door":0,"ds":0,"sight":20,"light":20,"sound":20,"dir":0,"threshold":{"light":null,"sight":null,"sound":null,"attenuation":false}},
        {"_id":"AYdYzqQH09SxB2wV","flags":{},"c":[2037,1462,2062,1300],"move":20,"door":0,"ds":0,"sight":20,"light":20,"sound":20,"dir":0,"threshold":{"light":null,"sight":null,"sound":null,"attenuation":false}},
        {"_id":"c2tOsl01WS5YX3Kn","flags":{},"c":[2062,1300,2012,1050],"move":20,"door":0,"ds":0,"sight":20,"light":20,"sound":20,"dir":0,"threshold":{"light":null,"sight":null,"sound":null,"attenuation":false}},
        {"_id":"5yBHZ91sWPXlyThK","flags":{},"c":[2012,1050,1875,812],"move":20,"door":0,"ds":0,"sight":20,"light":20,"sound":20,"dir":0,"threshold":{"light":null,"sight":null,"sound":null,"attenuation":false}},
        {"_id":"elgo9aQh3PN7Rg30","flags":{},"c":[1875,812,1637,687],"move":20,"door":0,"ds":0,"sight":20,"light":20,"sound":20,"dir":0,"threshold":{"light":null,"sight":null,"sound":null,"attenuation":false}},
        {"_id":"7vY37rtjyfxRD69R","flags":{},"c":[1637,687,1400,662],"move":20,"door":0,"ds":0,"sight":20,"light":20,"sound":20,"dir":0,"threshold":{"light":null,"sight":null,"sound":null,"attenuation":false}},
        {"_id":"MW23ikgNmjQSxh52","flags":{},"c":[1400,662,1175,687],"move":20,"door":0,"ds":0,"sight":20,"light":20,"sound":20,"dir":0,"threshold":{"light":null,"sight":null,"sound":null,"attenuation":false}},
        {"_id":"C3XMGPDWUvFlDzLQ","flags":{},"c":[1175,687,1000,800],"move":20,"door":0,"ds":0,"sight":20,"light":20,"sound":20,"dir":0,"threshold":{"light":null,"sight":null,"sound":null,"attenuation":false}},
        {"_id":"qhPgTrckswwnBP5c","flags":{},"c":[1000,800,825,1000],"move":20,"door":0,"ds":0,"sight":20,"light":20,"sound":20,"dir":0,"threshold":{"light":null,"sight":null,"sound":null,"attenuation":false}},
        {"_id":"QPj9cAYwHi42iNuZ","flags":{},"c":[825,1000,762,1300],"move":20,"door":0,"ds":0,"sight":20,"light":20,"sound":20,"dir":0,"threshold":{"light":null,"sight":null,"sound":null,"attenuation":false}},
        {"_id":"ji2y67yYO5jPuWTJ","flags":{},"c":[825,1000,762,1300],"move":20,"door":0,"ds":0,"sight":20,"light":20,"sound":20,"dir":0,"threshold":{"light":null,"sight":null,"sound":null,"attenuation":false}},
        {"_id":"sLcOJelrniDmGO21","flags":{},"c":[762,1300,800,1550],"move":20,"door":0,"ds":0,"sight":20,"light":20,"sound":20,"dir":0,"threshold":{"light":null,"sight":null,"sound":null,"attenuation":false}},
        {"_id":"hApdJhWWaiYfrTQP","flags":{},"c":[800,1550,925,1725],"move":20,"door":0,"ds":0,"sight":20,"light":20,"sound":20,"dir":0,"threshold":{"light":null,"sight":null,"sound":null,"attenuation":false}},
        {"_id":"cdfs19mcVpdxCIry","flags":{},"c":[925,1725,1087,1862],"move":20,"door":0,"ds":0,"sight":20,"light":20,"sound":20,"dir":0,"threshold":{"light":null,"sight":null,"sound":null,"attenuation":false}},
        {"_id":"KLUCxHUHOMtRaPLO","flags":{},"c":[1087,1862,1262,1925],"move":20,"door":0,"ds":0,"sight":20,"light":20,"sound":20,"dir":0,"threshold":{"light":null,"sight":null,"sound":null,"attenuation":false}},
        {"_id":"GakPYyUqXTzPusvB","flags":{},"c":[1262,1925,1400,1937],"move":20,"door":0,"ds":0,"sight":20,"light":20,"sound":20,"dir":0,"threshold":{"light":null,"sight":null,"sound":null,"attenuation":false}},
        {"_id":"VQHnjorBKG3aBBuH","flags":{},"c":[1712,1862,1612,1912],"move":20,"door":0,"ds":0,"sight":20,"light":20,"sound":20,"dir":0,"threshold":{"light":null,"sight":null,"sound":null,"attenuation":false}},
        {"_id":"LQc6HEn6psUVCAdU","flags":{},"c":[1962,1787,2012,1650],"move":20,"door":0,"ds":0,"sight":20,"light":20,"sound":20,"dir":0,"threshold":{"light":null,"sight":null,"sound":null,"attenuation":false}},
        {"_id":"75aBdh5Jpdhncjdh","flags":{},"c":[2012,1650,2112,1575],"move":20,"door":0,"ds":0,"sight":20,"light":20,"sound":20,"dir":0,"threshold":{"light":null,"sight":null,"sound":null,"attenuation":false}},
        {"_id":"hdO5jNg3Wph3HEd8","flags":{},"c":[2112,1575,2200,1562],"move":20,"door":0,"ds":0,"sight":20,"light":20,"sound":20,"dir":0,"threshold":{"light":null,"sight":null,"sound":null,"attenuation":false}},
        {"_id":"4wsRgZHv7AIfAKVE","flags":{},"c":[2200,1562,2325,1600],"move":20,"door":0,"ds":0,"sight":20,"light":20,"sound":20,"dir":0,"threshold":{"light":null,"sight":null,"sound":null,"attenuation":false}},
        {"_id":"1ydzkGYUot5DSt4v","flags":{},"c":[2325,1600,2412,1687],"move":20,"door":0,"ds":0,"sight":20,"light":20,"sound":20,"dir":0,"threshold":{"light":null,"sight":null,"sound":null,"attenuation":false}},
        {"_id":"Z4DLW531oHRtroTf","flags":{},"c":[2412,1687,2437,1800],"move":20,"door":0,"ds":0,"sight":20,"light":20,"sound":20,"dir":0,"threshold":{"light":null,"sight":null,"sound":null,"attenuation":false}},
        {"_id":"tKeDa78y2tcHYJzS","flags":{},"c":[2437,1800,2412,1912],"move":20,"door":0,"ds":0,"sight":20,"light":20,"sound":20,"dir":0,"threshold":{"light":null,"sight":null,"sound":null,"attenuation":false}},
        {"_id":"unGTRlcrFCrcjueQ","flags":{},"c":[2412,1912,2325,2000],"move":20,"door":0,"ds":0,"sight":20,"light":20,"sound":20,"dir":0,"threshold":{"light":null,"sight":null,"sound":null,"attenuation":false}},
        {"_id":"iQx9cu9AmOJjuXZ0","flags":{},"c":[2325,2000,2200,2037],"move":20,"door":0,"ds":0,"sight":20,"light":20,"sound":20,"dir":0,"threshold":{"light":null,"sight":null,"sound":null,"attenuation":false}},
        {"_id":"zsUVymLubwiKAizr","flags":{},"c":[2200,2037,2087,2012],"move":20,"door":0,"ds":0,"sight":20,"light":20,"sound":20,"dir":0,"threshold":{"light":null,"sight":null,"sound":null,"attenuation":false}},
        {"_id":"3bldqe6rDwJpH3fs","flags":{},"c":[2087,2012,1987,1900],"move":20,"door":0,"ds":0,"sight":20,"light":20,"sound":20,"dir":0,"threshold":{"light":null,"sight":null,"sound":null,"attenuation":false}},
        {"_id":"xZ1xSDq6kUmiNRiE","flags":{},"c":[1987,1900,1962,1787],"move":20,"door":0,"ds":0,"sight":20,"light":20,"sound":20,"dir":0,"threshold":{"light":null,"sight":null,"sound":null,"attenuation":false}},
        {"_id":"CeqzylTpvl2thju2","flags":{},"c":[2012,650,2112,575],"move":20,"door":0,"ds":0,"sight":20,"light":20,"sound":20,"dir":0,"threshold":{"light":null,"sight":null,"sound":null,"attenuation":false}},
        {"_id":"6sJjl33hN6hqxwJp","flags":{},"c":[2112,575,2200,562],"move":20,"door":0,"ds":0,"sight":20,"light":20,"sound":20,"dir":0,"threshold":{"light":null,"sight":null,"sound":null,"attenuation":false}},
        {"_id":"Ki4if7zhWSlJPibq","flags":{},"c":[2200,562,2325,600],"move":20,"door":0,"ds":0,"sight":20,"light":20,"sound":20,"dir":0,"threshold":{"light":null,"sight":null,"sound":null,"attenuation":false}},
        {"_id":"wy0AC5P9pIZpmym0","flags":{},"c":[2412,687,2437,800],"move":20,"door":0,"ds":0,"sight":20,"light":20,"sound":20,"dir":0,"threshold":{"light":null,"sight":null,"sound":null,"attenuation":false}},
        {"_id":"xY6CsHXkwr7NunFG","flags":{},"c":[2437,800,2412,912],"move":20,"door":0,"ds":0,"sight":20,"light":20,"sound":20,"dir":0,"threshold":{"light":null,"sight":null,"sound":null,"attenuation":false}},
        {"_id":"gDJHIxP1mZXRP3ZN","flags":{},"c":[2412,912,2325,1000],"move":20,"door":0,"ds":0,"sight":20,"light":20,"sound":20,"dir":0,"threshold":{"light":null,"sight":null,"sound":null,"attenuation":false}},
        {"_id":"Sdy8Cyl5lkRWOagd","flags":{},"c":[2200,1037,2087,1012],"move":20,"door":0,"ds":0,"sight":20,"light":20,"sound":20,"dir":0,"threshold":{"light":null,"sight":null,"sound":null,"attenuation":false}},
        {"_id":"qikIO1doV6jgiI4f","flags":{},"c":[2087,1012,1987,900],"move":20,"door":0,"ds":0,"sight":20,"light":20,"sound":20,"dir":0,"threshold":{"light":null,"sight":null,"sound":null,"attenuation":false}},
        {"_id":"VCV2cCzwTFITVHyP","flags":{},"c":[1987,900,1962,787],"move":20,"door":0,"ds":0,"sight":20,"light":20,"sound":20,"dir":0,"threshold":{"light":null,"sight":null,"sound":null,"attenuation":false}},
        {"_id":"cjDsJ88bmN2XTuFR","flags":{},"c":[2325,600,2412,687],"move":20,"door":0,"ds":0,"sight":20,"light":20,"sound":20,"dir":0,"threshold":{"light":null,"sight":null,"sound":null,"attenuation":false}},
        {"_id":"gV3zGSuBbI0gehQr","flags":{},"c":[1962,787,2012,650],"move":20,"door":0,"ds":0,"sight":20,"light":20,"sound":20,"dir":0,"threshold":{"light":null,"sight":null,"sound":null,"attenuation":false}},
        {"_id":"sqe0tLQRm23ohmSw","flags":{},"c":[2325,1000,2200,1037],"move":20,"door":0,"ds":0,"sight":20,"light":20,"sound":20,"dir":0,"threshold":{"light":null,"sight":null,"sound":null,"attenuation":false}},
        {"_id":"5e07c3E5tJV1nsKP","flags":{},"c":[2612,662,2712,587],"move":20,"door":0,"ds":0,"sight":20,"light":20,"sound":20,"dir":0,"threshold":{"light":null,"sight":null,"sound":null,"attenuation":false}},
        {"_id":"6N4v8l8YMSWFKAz4","flags":{},"c":[2712,587,2800,574],"move":20,"door":0,"ds":0,"sight":20,"light":20,"sound":20,"dir":0,"threshold":{"light":null,"sight":null,"sound":null,"attenuation":false}},
        {"_id":"WyWGS3nPDutu1aRb","flags":{},"c":[2800,574,2925,612],"move":20,"door":0,"ds":0,"sight":20,"light":20,"sound":20,"dir":0,"threshold":{"light":null,"sight":null,"sound":null,"attenuation":false}},
        {"_id":"kaXY3G0YHC5dJld7","flags":{},"c":[3012,699,3037,812],"move":20,"door":0,"ds":0,"sight":20,"light":20,"sound":20,"dir":0,"threshold":{"light":null,"sight":null,"sound":null,"attenuation":false}},
        {"_id":"doZ4B6mX14NhGpIx","flags":{},"c":[3037,812,3012,924],"move":20,"door":0,"ds":0,"sight":20,"light":20,"sound":20,"dir":0,"threshold":{"light":null,"sight":null,"sound":null,"attenuation":false}},
        {"_id":"cDMV3uKLZaOfi3fg","flags":{},"c":[3012,924,2925,1012],"move":20,"door":0,"ds":0,"sight":20,"light":20,"sound":20,"dir":0,"threshold":{"light":null,"sight":null,"sound":null,"attenuation":false}},
        {"_id":"WVOmfwqlhQphOLNb","flags":{},"c":[2800,1049,2687,1024],"move":20,"door":0,"ds":0,"sight":20,"light":20,"sound":20,"dir":0,"threshold":{"light":null,"sight":null,"sound":null,"attenuation":false}},
        {"_id":"Hk0vqoTMCPPj0H4b","flags":{},"c":[2687,1024,2587,912],"move":20,"door":0,"ds":0,"sight":20,"light":20,"sound":20,"dir":0,"threshold":{"light":null,"sight":null,"sound":null,"attenuation":false}},
        {"_id":"dwQUZbzO1XVUR04v","flags":{},"c":[2587,912,2562,799],"move":20,"door":0,"ds":0,"sight":20,"light":20,"sound":20,"dir":0,"threshold":{"light":null,"sight":null,"sound":null,"attenuation":false}},
        {"_id":"pcVKbIbV5tkWNUVy","flags":{},"c":[2925,612,3012,699],"move":20,"door":0,"ds":0,"sight":20,"light":20,"sound":20,"dir":0,"threshold":{"light":null,"sight":null,"sound":null,"attenuation":false}},
        {"_id":"DFYt985Isyfs42BY","flags":{},"c":[2562,799,2612,662],"move":20,"door":0,"ds":0,"sight":20,"light":20,"sound":20,"dir":0,"threshold":{"light":null,"sight":null,"sound":null,"attenuation":false}},
        {"_id":"UStEpEnt7k1w4vH8","flags":{},"c":[2925,1012,2800,1049],"move":20,"door":0,"ds":0,"sight":20,"light":20,"sound":20,"dir":0,"threshold":{"light":null,"sight":null,"sound":null,"attenuation":false}},
        {"_id":"sfOwFoW3CuPtcy5A","flags":{},"c":[2587,1437,2512,1500],"move":20,"door":0,"ds":0,"sight":20,"light":20,"sound":20,"dir":0,"threshold":{"light":null,"sight":null,"sound":null,"attenuation":false}},
        {"_id":"eBIGvJhWX8epH3hR","flags":{},"c":[2512,1500,2487,1600],"move":20,"door":0,"ds":0,"sight":20,"light":20,"sound":20,"dir":0,"threshold":{"light":null,"sight":null,"sound":null,"attenuation":false}},
        {"_id":"O6ABSqAz0IY6YVLP","flags":{},"c":[2487,1600,2525,1712],"move":20,"door":0,"ds":0,"sight":20,"light":20,"sound":20,"dir":0,"threshold":{"light":null,"sight":null,"sound":null,"attenuation":false}},
        {"_id":"Mohx6j9JJ8YHGYZu","flags":{},"c":[2525,1712,2587,1775],"move":20,"door":0,"ds":0,"sight":20,"light":20,"sound":20,"dir":0,"threshold":{"light":null,"sight":null,"sound":null,"attenuation":false}},
        {"_id":"xWnVUCozY3crWLLZ","flags":{},"c":[2587,1775,2712,1800],"move":20,"door":0,"ds":0,"sight":20,"light":20,"sound":20,"dir":0,"threshold":{"light":null,"sight":null,"sound":null,"attenuation":false}},
        {"_id":"wbd9Uz0sTeKEq9rU","flags":{},"c":[2587,1437,2700,1400],"move":20,"door":0,"ds":0,"sight":20,"light":20,"sound":20,"dir":0,"threshold":{"light":null,"sight":null,"sound":null,"attenuation":false}},
        {"_id":"CIpBDkCytj3kU1nb","flags":{},"c":[2587,1437,2587,1325],"move":20,"door":0,"ds":0,"sight":20,"light":20,"sound":20,"dir":0,"threshold":{"light":null,"sight":null,"sound":null,"attenuation":false}},
        {"_id":"yGMSgf4QJ0uM3f6R","flags":{},"c":[2587,1325,2650,1212],"move":20,"door":0,"ds":0,"sight":20,"light":20,"sound":20,"dir":0,"threshold":{"light":null,"sight":null,"sound":null,"attenuation":false}},
        {"_id":"hfpmHjJQHV0Zq5du","flags":{},"c":[2650,1212,2750,1175],"move":20,"door":0,"ds":0,"sight":20,"light":20,"sound":20,"dir":0,"threshold":{"light":null,"sight":null,"sound":null,"attenuation":false}},
        {"_id":"UELyPjdZaqiB6IQK","flags":{},"c":[2750,1175,2862,1237],"move":20,"door":0,"ds":0,"sight":20,"light":20,"sound":20,"dir":0,"threshold":{"light":null,"sight":null,"sound":null,"attenuation":false}},
        {"_id":"wDaaKRfmaumM380e","flags":{},"c":[2862,1237,2912,1325],"move":20,"door":0,"ds":0,"sight":20,"light":20,"sound":20,"dir":0,"threshold":{"light":null,"sight":null,"sound":null,"attenuation":false}},
        {"_id":"Sq8P5zUtx427j0pc","flags":{},"c":[2912,1325,2912,1437],"move":20,"door":0,"ds":0,"sight":20,"light":20,"sound":20,"dir":0,"threshold":{"light":null,"sight":null,"sound":null,"attenuation":false}},
        {"_id":"DR1ODrz0yRMiTZ2e","flags":{},"c":[2912,1437,2800,1400],"move":20,"door":0,"ds":0,"sight":20,"light":20,"sound":20,"dir":0,"threshold":{"light":null,"sight":null,"sound":null,"attenuation":false}},
        {"_id":"hLmNG0oDhk2CmR9I","flags":{},"c":[2912,1437,2987,1487],"move":20,"door":0,"ds":0,"sight":20,"light":20,"sound":20,"dir":0,"threshold":{"light":null,"sight":null,"sound":null,"attenuation":false}},
        {"_id":"dKIJLL7CxUr4Pj5t","flags":{},"c":[2987,1487,3000,1537],"move":20,"door":0,"ds":0,"sight":20,"light":20,"sound":20,"dir":0,"threshold":{"light":null,"sight":null,"sound":null,"attenuation":false}},
        {"_id":"DWMKuDF9mGOqIeM5","flags":{},"c":[3000,1662,2962,1725],"move":20,"door":0,"ds":0,"sight":20,"light":20,"sound":20,"dir":0,"threshold":{"light":null,"sight":null,"sound":null,"attenuation":false}},
        {"_id":"Zgn9Xz3EHKMeJXdb","flags":{},"c":[2962,1725,2912,1775],"move":20,"door":0,"ds":0,"sight":20,"light":20,"sound":20,"dir":0,"threshold":{"light":null,"sight":null,"sound":null,"attenuation":false}},
        {"_id":"VXNIs1FbTcbfROHW","flags":{},"c":[2912,1775,2800,1800],"move":20,"door":0,"ds":0,"sight":20,"light":20,"sound":20,"dir":0,"threshold":{"light":null,"sight":null,"sound":null,"attenuation":false}},
        {"_id":"Un4RPFqkCLPKMS9y","flags":{},"c":[2700,1400,2800,1400],"move":20,"door":1,"ds":0,"sight":20,"light":20,"sound":20,"dir":0,"threshold":{"light":null,"sight":null,"sound":null,"attenuation":false}},
        {"_id":"taPvEx3vCPAUXMuQ","flags":{},"c":[2712,1800,2800,1800],"move":20,"door":1,"ds":0,"sight":20,"light":20,"sound":20,"dir":0,"threshold":{"light":null,"sight":null,"sound":null,"attenuation":false}}
    ],
    "lights": [
    
    ],
    "drawings": [
    
    ]
}
