{
    "walls": [
        {"_id":"A7r8RByI6sk655L0","c":[4600,1900,4600,2200],"move":20,"sound":20,"dir":0,"door":0,"ds":0,"flags":{},"sight":20,"light":20,"threshold":{"light":null,"sight":null,"sound":null,"attenuation":false}},
        {"_id":"66GMEPD3Yn1rnH7d","c":[4600,2200,4500,2200],"move":20,"sound":20,"dir":0,"door":0,"ds":0,"flags":{},"sight":20,"light":20,"threshold":{"light":null,"sight":null,"sound":null,"attenuation":false}},
        {"_id":"lU5vA3XxnqOi6IDt","c":[4500,2200,4500,2100],"move":20,"sound":20,"dir":0,"door":0,"ds":0,"flags":{},"sight":20,"light":20,"threshold":{"light":null,"sight":null,"sound":null,"attenuation":false}},
        {"_id":"H6TmgKYw3PSK82nj","c":[4500,2100,3700,2100],"move":20,"sound":20,"dir":0,"door":0,"ds":0,"flags":{},"sight":20,"light":20,"threshold":{"light":null,"sight":null,"sound":null,"attenuation":false}},
        {"_id":"1w8A5nwwNz9yDjQW","c":[3700,2100,3700,2200],"move":20,"sound":20,"dir":0,"door":0,"ds":0,"flags":{},"sight":20,"light":20,"threshold":{"light":null,"sight":null,"sound":null,"attenuation":false}},
        {"_id":"jvGoVMW15yHtD590","c":[3700,2200,3600,2200],"move":20,"sound":20,"dir":0,"door":0,"ds":0,"flags":{},"sight":20,"light":20,"threshold":{"light":null,"sight":null,"sound":null,"attenuation":false}},
        {"_id":"qgh3bioWefsZjdCR","c":[3600,2200,3600,1900],"move":20,"sound":20,"dir":0,"door":0,"ds":0,"flags":{},"sight":20,"light":20,"threshold":{"light":null,"sight":null,"sound":null,"attenuation":false}},
        {"_id":"9kNanpMCrb7QyQUu","c":[3600,1900,3700,1900],"move":20,"sound":20,"dir":0,"door":0,"ds":0,"flags":{},"sight":20,"light":20,"threshold":{"light":null,"sight":null,"sound":null,"attenuation":false}},
        {"_id":"9Dy7iUJ0NWuIotvm","c":[3700,1900,3700,2000],"move":20,"sound":20,"dir":0,"door":0,"ds":0,"flags":{},"sight":20,"light":20,"threshold":{"light":null,"sight":null,"sound":null,"attenuation":false}},
        {"_id":"1Arb5LmEzxFT5IPb","c":[3700,2000,4500,2000],"move":20,"sound":20,"dir":0,"door":0,"ds":0,"flags":{},"sight":20,"light":20,"threshold":{"light":null,"sight":null,"sound":null,"attenuation":false}},
        {"_id":"mdtZa4jZdKtyMDjw","c":[4500,2000,4500,1900],"move":20,"sound":20,"dir":0,"door":0,"ds":0,"flags":{},"sight":20,"light":20,"threshold":{"light":null,"sight":null,"sound":null,"attenuation":false}},
        {"_id":"QubAsH0AAAaJ5txQ","c":[4500,1900,4600,1900],"move":20,"sound":20,"dir":0,"door":0,"ds":0,"flags":{},"sight":20,"light":20,"threshold":{"light":null,"sight":null,"sound":null,"attenuation":false}},
        {"_id":"UNdbdWcvOHESK16D","c":[4600,2500,4600,2700],"move":20,"sound":20,"dir":0,"door":0,"ds":0,"flags":{},"sight":20,"light":20,"threshold":{"light":null,"sight":null,"sound":null,"attenuation":false}},
        {"_id":"2xQM4UymLOaeJCSh","c":[4600,2700,3700,2700],"move":20,"sound":20,"dir":0,"door":0,"ds":0,"flags":{},"sight":20,"light":20,"threshold":{"light":null,"sight":null,"sound":null,"attenuation":false}},
        {"_id":"6PKAZQ4h4MZ2ukmF","c":[3700,2700,3700,3000],"move":20,"sound":20,"dir":0,"door":0,"ds":0,"flags":{},"sight":20,"light":20,"threshold":{"light":null,"sight":null,"sound":null,"attenuation":false}},
        {"_id":"iM1JFFpvD1tEWK9H","c":[3700,3000,1900,3000],"move":20,"sound":20,"dir":0,"door":0,"ds":0,"flags":{},"sight":20,"light":20,"threshold":{"light":null,"sight":null,"sound":null,"attenuation":false}},
        {"_id":"izHuQnXzn2cI4byn","c":[1900,3000,1900,3100],"move":20,"sound":20,"dir":0,"door":0,"ds":0,"flags":{},"sight":20,"light":20,"threshold":{"light":null,"sight":null,"sound":null,"attenuation":false}},
        {"_id":"F2mmM3AYpc018awV","c":[1900,3100,1800,3100],"move":20,"sound":20,"dir":0,"door":0,"ds":0,"flags":{},"sight":20,"light":20,"threshold":{"light":null,"sight":null,"sound":null,"attenuation":false}},
        {"_id":"qBNrnaTmtPcbiD8X","c":[1800,3100,1800,2900],"move":20,"sound":20,"dir":0,"door":0,"ds":0,"flags":{},"sight":20,"light":20,"threshold":{"light":null,"sight":null,"sound":null,"attenuation":false}},
        {"_id":"EHakd9bYpSjdVk0i","c":[1800,2900,2000,2900],"move":20,"sound":20,"dir":0,"door":0,"ds":0,"flags":{},"sight":20,"light":20,"threshold":{"light":null,"sight":null,"sound":null,"attenuation":false}},
        {"_id":"UoiI5t3abQoEfVaI","c":[2000,2900,2000,2400],"move":20,"sound":20,"dir":0,"door":0,"ds":0,"flags":{},"sight":20,"light":20,"threshold":{"light":null,"sight":null,"sound":null,"attenuation":false}},
        {"_id":"363INzjFOL8XxSfM","c":[2000,2400,1500,2400],"move":20,"sound":20,"dir":0,"door":0,"ds":0,"flags":{},"sight":20,"light":20,"threshold":{"light":null,"sight":null,"sound":null,"attenuation":false}},
        {"_id":"hslN8Lbdoh7oenaH","c":[1500,2400,1500,2300],"move":20,"sound":20,"dir":0,"door":0,"ds":0,"flags":{},"sight":20,"light":20,"threshold":{"light":null,"sight":null,"sound":null,"attenuation":false}},
        {"_id":"CCJR7PbOonBinXVq","c":[1500,2300,2000,2300],"move":20,"sound":20,"dir":0,"door":0,"ds":0,"flags":{},"sight":20,"light":20,"threshold":{"light":null,"sight":null,"sound":null,"attenuation":false}},
        {"_id":"jOwTeRnzMP2J4M2y","c":[2000,2300,2000,2000],"move":20,"sound":20,"dir":0,"door":0,"ds":0,"flags":{},"sight":20,"light":20,"threshold":{"light":null,"sight":null,"sound":null,"attenuation":false}},
        {"_id":"rN9v63z4WKke5JTC","c":[2000,2000,2100,2000],"move":20,"sound":20,"dir":0,"door":0,"ds":0,"flags":{},"sight":20,"light":20,"threshold":{"light":null,"sight":null,"sound":null,"attenuation":false}},
        {"_id":"4iPHeS7WMzwosT1H","c":[2100,2000,2100,2900],"move":20,"sound":20,"dir":0,"door":0,"ds":0,"flags":{},"sight":20,"light":20,"threshold":{"light":null,"sight":null,"sound":null,"attenuation":false}},
        {"_id":"SV0oyP8NY0fvh0wt","c":[2100,2900,2600,2900],"move":20,"sound":20,"dir":0,"door":0,"ds":0,"flags":{},"sight":20,"light":20,"threshold":{"light":null,"sight":null,"sound":null,"attenuation":false}},
        {"_id":"T7ONXWM3xMCCkGiV","c":[2600,2900,2600,2700],"move":20,"sound":20,"dir":0,"door":0,"ds":0,"flags":{},"sight":20,"light":20,"threshold":{"light":null,"sight":null,"sound":null,"attenuation":false}},
        {"_id":"BxBsbFseBjKWDZDO","c":[2600,2700,2700,2700],"move":20,"sound":20,"dir":0,"door":0,"ds":0,"flags":{},"sight":20,"light":20,"threshold":{"light":null,"sight":null,"sound":null,"attenuation":false}},
        {"_id":"WlLQvpfCSld1RG4k","c":[2700,2700,2700,2900],"move":20,"sound":20,"dir":0,"door":0,"ds":0,"flags":{},"sight":20,"light":20,"threshold":{"light":null,"sight":null,"sound":null,"attenuation":false}},
        {"_id":"Hme8r8A5ai0s9hFl","c":[2700,2900,3600,2900],"move":20,"sound":20,"dir":0,"door":0,"ds":0,"flags":{},"sight":20,"light":20,"threshold":{"light":null,"sight":null,"sound":null,"attenuation":false}},
        {"_id":"xpuh6nRcatQCTarM","c":[3600,2900,3600,2500],"move":20,"sound":20,"dir":0,"door":0,"ds":0,"flags":{},"sight":20,"light":20,"threshold":{"light":null,"sight":null,"sound":null,"attenuation":false}},
        {"_id":"5UWEQGQWzmyZWTIC","c":[3600,2500,3700,2500],"move":20,"sound":20,"dir":0,"door":0,"ds":0,"flags":{},"sight":20,"light":20,"threshold":{"light":null,"sight":null,"sound":null,"attenuation":false}},
        {"_id":"LadnKrYHrwkkbjUW","c":[3700,2500,3700,2600],"move":20,"sound":20,"dir":0,"door":0,"ds":0,"flags":{},"sight":20,"light":20,"threshold":{"light":null,"sight":null,"sound":null,"attenuation":false}},
        {"_id":"bfcHEF0UHaFE1JCb","c":[3700,2600,4500,2600],"move":20,"sound":20,"dir":0,"door":0,"ds":0,"flags":{},"sight":20,"light":20,"threshold":{"light":null,"sight":null,"sound":null,"attenuation":false}},
        {"_id":"5MC9VPT1JiChPTlX","c":[4500,2600,4500,2500],"move":20,"sound":20,"dir":0,"door":0,"ds":0,"flags":{},"sight":20,"light":20,"threshold":{"light":null,"sight":null,"sound":null,"attenuation":false}},
        {"_id":"oaBrybJ7yyL5ySK3","c":[4500,2500,4600,2500],"move":20,"sound":20,"dir":0,"door":0,"ds":0,"flags":{},"sight":20,"light":20,"threshold":{"light":null,"sight":null,"sound":null,"attenuation":false}},
        {"_id":"FPPPVXiXoKpHsu6w","c":[4600,1300,4600,1600],"move":20,"sound":20,"dir":0,"door":0,"ds":0,"flags":{},"sight":20,"light":20,"threshold":{"light":null,"sight":null,"sound":null,"attenuation":false}},
        {"_id":"xmP3ewHiVWIxCNIu","c":[4600,1600,4500,1600],"move":20,"sound":20,"dir":0,"door":0,"ds":0,"flags":{},"sight":20,"light":20,"threshold":{"light":null,"sight":null,"sound":null,"attenuation":false}},
        {"_id":"9aURdgg6HutPKRrO","c":[4500,1600,4500,1500],"move":20,"sound":20,"dir":0,"door":0,"ds":0,"flags":{},"sight":20,"light":20,"threshold":{"light":null,"sight":null,"sound":null,"attenuation":false}},
        {"_id":"6vhEIgji32ZrQPEI","c":[4500,1500,3700,1500],"move":20,"sound":20,"dir":0,"door":0,"ds":0,"flags":{},"sight":20,"light":20,"threshold":{"light":null,"sight":null,"sound":null,"attenuation":false}},
        {"_id":"N2ZXTPrjLbA1P89m","c":[3700,1500,3700,1600],"move":20,"sound":20,"dir":0,"door":0,"ds":0,"flags":{},"sight":20,"light":20,"threshold":{"light":null,"sight":null,"sound":null,"attenuation":false}},
        {"_id":"k4vMkzDFFFf8lM8A","c":[3700,1600,3600,1600],"move":20,"sound":20,"dir":0,"door":0,"ds":0,"flags":{},"sight":20,"light":20,"threshold":{"light":null,"sight":null,"sound":null,"attenuation":false}},
        {"_id":"Y3qb63X5EbR8KAXb","c":[3600,1600,3600,1500],"move":20,"sound":20,"dir":0,"door":0,"ds":0,"flags":{},"sight":20,"light":20,"threshold":{"light":null,"sight":null,"sound":null,"attenuation":false}},
        {"_id":"jqdnBlaYERAoArUW","c":[3600,1500,3300,1500],"move":20,"sound":20,"dir":0,"door":0,"ds":0,"flags":{},"sight":20,"light":20,"threshold":{"light":null,"sight":null,"sound":null,"attenuation":false}},
        {"_id":"7N4cW0GOEdCfrEiz","c":[3300,1500,3300,1400],"move":20,"sound":20,"dir":0,"door":0,"ds":0,"flags":{},"sight":20,"light":20,"threshold":{"light":null,"sight":null,"sound":null,"attenuation":false}},
        {"_id":"NVyIP5J1TfKmc9fP","c":[3300,1400,3600,1400],"move":20,"sound":20,"dir":0,"door":0,"ds":0,"flags":{},"sight":20,"light":20,"threshold":{"light":null,"sight":null,"sound":null,"attenuation":false}},
        {"_id":"EKpx4CqQDfcro3VL","c":[3600,1400,3600,1000],"move":20,"sound":20,"dir":0,"door":0,"ds":0,"flags":{},"sight":20,"light":20,"threshold":{"light":null,"sight":null,"sound":null,"attenuation":false}},
        {"_id":"xxF2NPPPSAcLzzvA","c":[3600,1000,3700,1000],"move":20,"sound":20,"dir":0,"door":0,"ds":0,"flags":{},"sight":20,"light":20,"threshold":{"light":null,"sight":null,"sound":null,"attenuation":false}},
        {"_id":"brWwZwY8A9j4u6xa","c":[3700,1000,3700,1400],"move":20,"sound":20,"dir":0,"door":0,"ds":0,"flags":{},"sight":20,"light":20,"threshold":{"light":null,"sight":null,"sound":null,"attenuation":false}},
        {"_id":"s7b0bfBsB2rE9riY","c":[3700,1400,4500,1400],"move":20,"sound":20,"dir":0,"door":0,"ds":0,"flags":{},"sight":20,"light":20,"threshold":{"light":null,"sight":null,"sound":null,"attenuation":false}},
        {"_id":"lU2ufRAe2klcjlCz","c":[4500,1400,4500,1300],"move":20,"sound":20,"dir":0,"door":0,"ds":0,"flags":{},"sight":20,"light":20,"threshold":{"light":null,"sight":null,"sound":null,"attenuation":false}},
        {"_id":"puEsL7zSK7RTU0Qg","c":[4500,1300,4600,1300],"move":20,"sound":20,"dir":0,"door":0,"ds":0,"flags":{},"sight":20,"light":20,"threshold":{"light":null,"sight":null,"sound":null,"attenuation":false}},
        {"_id":"gTbRCuaEqwjQxDYB","c":[4500,1000,4600,1000],"move":20,"sound":20,"dir":0,"door":0,"ds":0,"flags":{},"sight":20,"light":20,"threshold":{"light":null,"sight":null,"sound":null,"attenuation":false}},
        {"_id":"dMPXrAKXxh35e7h7","c":[4600,1000,4600,800],"move":20,"sound":20,"dir":0,"door":0,"ds":0,"flags":{},"sight":20,"light":20,"threshold":{"light":null,"sight":null,"sound":null,"attenuation":false}},
        {"_id":"P4E1jcSzv4lThz3z","c":[4600,800,2000,800],"move":20,"sound":20,"dir":0,"door":0,"ds":0,"flags":{},"sight":20,"light":20,"threshold":{"light":null,"sight":null,"sound":null,"attenuation":false}},
        {"_id":"eNbnzEPuQZhneYUj","c":[2000,800,2000,1200],"move":20,"sound":20,"dir":0,"door":0,"ds":0,"flags":{},"sight":20,"light":20,"threshold":{"light":null,"sight":null,"sound":null,"attenuation":false}},
        {"_id":"Ubk7dBndXhxoil1z","c":[2000,1200,1100,1200],"move":20,"sound":20,"dir":0,"door":0,"ds":0,"flags":{},"sight":20,"light":20,"threshold":{"light":null,"sight":null,"sound":null,"attenuation":false}},
        {"_id":"k0OuBAwB9STkhKcs","c":[1100,1200,1100,3000],"move":20,"sound":20,"dir":0,"door":0,"ds":0,"flags":{},"sight":20,"light":20,"threshold":{"light":null,"sight":null,"sound":null,"attenuation":false}},
        {"_id":"DkdLa4fSUBZkpYK8","c":[1100,3000,1500,3000],"move":20,"sound":20,"dir":0,"door":0,"ds":0,"flags":{},"sight":20,"light":20,"threshold":{"light":null,"sight":null,"sound":null,"attenuation":false}},
        {"_id":"kIMLBW9yP5lpVeDC","c":[1500,3000,1500,3100],"move":20,"sound":20,"dir":0,"door":0,"ds":0,"flags":{},"sight":20,"light":20,"threshold":{"light":null,"sight":null,"sound":null,"attenuation":false}},
        {"_id":"ddO8sVUw4xf68O3t","c":[1500,3100,1600,3100],"move":20,"sound":20,"dir":0,"door":0,"ds":0,"flags":{},"sight":20,"light":20,"threshold":{"light":null,"sight":null,"sound":null,"attenuation":false}},
        {"_id":"JazSb0iBxRQYwPwW","c":[1600,3100,1600,2900],"move":20,"sound":20,"dir":0,"door":0,"ds":0,"flags":{},"sight":20,"light":20,"threshold":{"light":null,"sight":null,"sound":null,"attenuation":false}},
        {"_id":"gzN1Z6NUAquN1F7D","c":[1600,2900,1200,2900],"move":20,"sound":20,"dir":0,"door":0,"ds":0,"flags":{},"sight":20,"light":20,"threshold":{"light":null,"sight":null,"sound":null,"attenuation":false}},
        {"_id":"UnPfq7aZv4vgDBor","c":[1200,2900,1200,2400],"move":20,"sound":20,"dir":0,"door":0,"ds":0,"flags":{},"sight":20,"light":20,"threshold":{"light":null,"sight":null,"sound":null,"attenuation":false}},
        {"_id":"VPrNReZUF8Kimfif","c":[1200,2400,1300,2400],"move":20,"sound":20,"dir":0,"door":0,"ds":0,"flags":{},"sight":20,"light":20,"threshold":{"light":null,"sight":null,"sound":null,"attenuation":false}},
        {"_id":"93w0wPCeFF8LIrhu","c":[1300,2400,1300,2300],"move":20,"sound":20,"dir":0,"door":0,"ds":0,"flags":{},"sight":20,"light":20,"threshold":{"light":null,"sight":null,"sound":null,"attenuation":false}},
        {"_id":"0JnNL1waWM9KwLxh","c":[1300,2300,1200,2300],"move":20,"sound":20,"dir":0,"door":0,"ds":0,"flags":{},"sight":20,"light":20,"threshold":{"light":null,"sight":null,"sound":null,"attenuation":false}},
        {"_id":"blFnJJts2nDiMlJP","c":[1200,2300,1200,1300],"move":20,"sound":20,"dir":0,"door":0,"ds":0,"flags":{},"sight":20,"light":20,"threshold":{"light":null,"sight":null,"sound":null,"attenuation":false}},
        {"_id":"riNylGgK9eqjALb1","c":[1200,1300,2100,1300],"move":20,"sound":20,"dir":0,"door":0,"ds":0,"flags":{},"sight":20,"light":20,"threshold":{"light":null,"sight":null,"sound":null,"attenuation":false}},
        {"_id":"hNTqWmpZbGG4pMpD","c":[2100,1300,2100,900],"move":20,"sound":20,"dir":0,"door":0,"ds":0,"flags":{},"sight":20,"light":20,"threshold":{"light":null,"sight":null,"sound":null,"attenuation":false}},
        {"_id":"uFJNLD7Mwp0whXFr","c":[2100,900,2700,900],"move":20,"sound":20,"dir":0,"door":0,"ds":0,"flags":{},"sight":20,"light":20,"threshold":{"light":null,"sight":null,"sound":null,"attenuation":false}},
        {"_id":"IByBDqeUi0LfMNiK","c":[2700,900,2700,1100],"move":20,"sound":20,"dir":0,"door":0,"ds":0,"flags":{},"sight":20,"light":20,"threshold":{"light":null,"sight":null,"sound":null,"attenuation":false}},
        {"_id":"1KY0eyqqDEhQQ2rq","c":[2700,1100,2800,1100],"move":20,"sound":20,"dir":0,"door":0,"ds":0,"flags":{},"sight":20,"light":20,"threshold":{"light":null,"sight":null,"sound":null,"attenuation":false}},
        {"_id":"S7FANw6HoglWBar3","c":[2800,1100,2800,900],"move":20,"sound":20,"dir":0,"door":0,"ds":0,"flags":{},"sight":20,"light":20,"threshold":{"light":null,"sight":null,"sound":null,"attenuation":false}},
        {"_id":"bxYrsm1HdevUxSd3","c":[2800,900,4500,900],"move":20,"sound":20,"dir":0,"door":0,"ds":0,"flags":{},"sight":20,"light":20,"threshold":{"light":null,"sight":null,"sound":null,"attenuation":false}},
        {"_id":"aGMne3etPAnuIH5W","c":[4500,900,4500,1000],"move":20,"sound":20,"dir":0,"door":0,"ds":0,"flags":{},"sight":20,"light":20,"threshold":{"light":null,"sight":null,"sound":null,"attenuation":false}},
        {"_id":"SVTdasn6eDxwTyqQ","c":[3100,1400,3100,1500],"move":20,"sound":20,"dir":0,"door":0,"ds":0,"flags":{},"sight":20,"light":20,"threshold":{"light":null,"sight":null,"sound":null,"attenuation":false}},
        {"_id":"LcstXxodb3q3oFHy","c":[3100,1500,2700,1500],"move":20,"sound":20,"dir":0,"door":0,"ds":0,"flags":{},"sight":20,"light":20,"threshold":{"light":null,"sight":null,"sound":null,"attenuation":false}},
        {"_id":"LVdcRoYvAafZ2k2f","c":[2700,1500,2700,1600],"move":20,"sound":20,"dir":0,"door":0,"ds":0,"flags":{},"sight":20,"light":20,"threshold":{"light":null,"sight":null,"sound":null,"attenuation":false}},
        {"_id":"ZbgRT6O88drzVE2K","c":[2700,1600,2600,1600],"move":20,"sound":20,"dir":0,"door":0,"ds":0,"flags":{},"sight":20,"light":20,"threshold":{"light":null,"sight":null,"sound":null,"attenuation":false}},
        {"_id":"zOkvZhRVkXhWsFTz","c":[2600,1600,2600,1500],"move":20,"sound":20,"dir":0,"door":0,"ds":0,"flags":{},"sight":20,"light":20,"threshold":{"light":null,"sight":null,"sound":null,"attenuation":false}},
        {"_id":"2vNc5URKExxtzUxp","c":[2600,1500,2100,1500],"move":20,"sound":20,"dir":0,"door":0,"ds":0,"flags":{},"sight":20,"light":20,"threshold":{"light":null,"sight":null,"sound":null,"attenuation":false}},
        {"_id":"x8QEvnh4XAy7GLY6","c":[2100,1500,2100,1800],"move":20,"sound":20,"dir":0,"door":0,"ds":0,"flags":{},"sight":20,"light":20,"threshold":{"light":null,"sight":null,"sound":null,"attenuation":false}},
        {"_id":"dlJPnAIrptXBFniG","c":[2100,1800,2000,1800],"move":20,"sound":20,"dir":0,"door":0,"ds":0,"flags":{},"sight":20,"light":20,"threshold":{"light":null,"sight":null,"sound":null,"attenuation":false}},
        {"_id":"C31kp3I9gBSU18gx","c":[2000,1800,2000,1400],"move":20,"sound":20,"dir":0,"door":0,"ds":0,"flags":{},"sight":20,"light":20,"threshold":{"light":null,"sight":null,"sound":null,"attenuation":false}},
        {"_id":"YO9VHBAGQrYhwTCo","c":[2000,1400,2700,1400],"move":20,"sound":20,"dir":0,"door":0,"ds":0,"flags":{},"sight":20,"light":20,"threshold":{"light":null,"sight":null,"sound":null,"attenuation":false}},
        {"_id":"ic3D74sh4ufp6KLq","c":[2700,1400,2700,1200],"move":20,"sound":20,"dir":0,"door":0,"ds":0,"flags":{},"sight":20,"light":20,"threshold":{"light":null,"sight":null,"sound":null,"attenuation":false}},
        {"_id":"pi9vg9iROg5iyL4c","c":[2700,1200,2800,1200],"move":20,"sound":20,"dir":0,"door":0,"ds":0,"flags":{},"sight":20,"light":20,"threshold":{"light":null,"sight":null,"sound":null,"attenuation":false}},
        {"_id":"rHJhoPsxbX6vmHQu","c":[2800,1200,2800,1400],"move":20,"sound":20,"dir":0,"door":0,"ds":0,"flags":{},"sight":20,"light":20,"threshold":{"light":null,"sight":null,"sound":null,"attenuation":false}},
        {"_id":"UEGoQILmFRyMuQfq","c":[2800,1400,3100,1400],"move":20,"sound":20,"dir":0,"door":0,"ds":0,"flags":{},"sight":20,"light":20,"threshold":{"light":null,"sight":null,"sound":null,"attenuation":false}},
        {"_id":"6moHYuW1LNRjtIw2","c":[2600,1800,2700,1800],"move":20,"sound":20,"dir":0,"door":0,"ds":0,"flags":{},"sight":20,"light":20,"threshold":{"light":null,"sight":null,"sound":null,"attenuation":false}},
        {"_id":"OzrPVureWRJmy2zV","c":[2700,1800,2700,2500],"move":20,"sound":20,"dir":0,"door":0,"ds":0,"flags":{},"sight":20,"light":20,"threshold":{"light":null,"sight":null,"sound":null,"attenuation":false}},
        {"_id":"b6Ohf8ih6tcuaIxC","c":[2700,2500,2600,2500],"move":20,"sound":20,"dir":0,"door":0,"ds":0,"flags":{},"sight":20,"light":20,"threshold":{"light":null,"sight":null,"sound":null,"attenuation":false}},
        {"_id":"2PUjkw6znVKOnKlg","c":[2600,2500,2600,1800],"move":20,"sound":20,"dir":0,"door":0,"ds":0,"flags":{},"sight":20,"light":20,"threshold":{"light":null,"sight":null,"sound":null,"attenuation":false}},
        {"_id":"qani5H8I4PLwdX3M","c":[1600,3062,1700,3062],"move":20,"sound":20,"dir":0,"door":1,"ds":0,"flags":{},"sight":20,"light":20,"threshold":{"light":null,"sight":null,"sound":null,"attenuation":false}},
        {"_id":"bslUOCkAaQwgmqrs","c":[1700,3062,1800,3062],"move":20,"sound":20,"dir":0,"door":1,"ds":0,"flags":{},"sight":20,"light":20,"threshold":{"light":null,"sight":null,"sound":null,"attenuation":false}},
        {"_id":"Cf1czwhzmDpDNuLc","c":[1300,2350,1400,2350],"move":20,"sound":20,"dir":0,"door":1,"ds":0,"flags":{},"sight":20,"light":20,"threshold":{"light":null,"sight":null,"sound":null,"attenuation":false}},
        {"_id":"n0LQrVHIOqIaIfBt","c":[1400,2350,1500,2350],"move":20,"sound":20,"dir":0,"door":1,"ds":0,"flags":{},"sight":20,"light":20,"threshold":{"light":null,"sight":null,"sound":null,"attenuation":false}},
        {"_id":"ibP9n025BXPjBgLn","c":[2050,1800,2050,1900],"move":20,"sound":20,"dir":0,"door":1,"ds":0,"flags":{},"sight":20,"light":20,"threshold":{"light":null,"sight":null,"sound":null,"attenuation":false}},
        {"_id":"Zzoct18UgdSyubBZ","c":[2050,1900,2050,2000],"move":20,"sound":20,"dir":0,"door":1,"ds":0,"flags":{},"sight":20,"light":20,"threshold":{"light":null,"sight":null,"sound":null,"attenuation":false}},
        {"_id":"23GwziGpH8cuhqoI","c":[2650,1600,2650,1700],"move":20,"sound":20,"dir":0,"door":1,"ds":0,"flags":{},"sight":20,"light":20,"threshold":{"light":null,"sight":null,"sound":null,"attenuation":false}},
        {"_id":"tz5p51m1wemEGsRm","c":[2650,1700,2650,1800],"move":20,"sound":20,"dir":0,"door":1,"ds":0,"flags":{},"sight":20,"light":20,"threshold":{"light":null,"sight":null,"sound":null,"attenuation":false}},
        {"_id":"K8bbZkuLa6A786Wo","c":[2650,2500,2650,2600],"move":20,"sound":20,"dir":0,"door":1,"ds":0,"flags":{},"sight":20,"light":20,"threshold":{"light":null,"sight":null,"sound":null,"attenuation":false}},
        {"_id":"qPZ0R3PNCqUSm6JG","c":[2650,2600,2650,2700],"move":20,"sound":20,"dir":0,"door":1,"ds":0,"flags":{},"sight":20,"light":20,"threshold":{"light":null,"sight":null,"sound":null,"attenuation":false}},
        {"_id":"EIqFXIC1jdVDnC68","c":[3650,2200,3650,2350],"move":20,"sound":20,"dir":0,"door":1,"ds":0,"flags":{},"sight":20,"light":20,"threshold":{"light":null,"sight":null,"sound":null,"attenuation":false}},
        {"_id":"Mfq2RzB9Ibn3qrGp","c":[3650,2350,3650,2500],"move":20,"sound":20,"dir":0,"door":1,"ds":0,"flags":{},"sight":20,"light":20,"threshold":{"light":null,"sight":null,"sound":null,"attenuation":false}},
        {"_id":"WPqL3dlBIcEOzI8H","c":[4550,2200,4550,2350],"move":20,"sound":20,"dir":0,"door":1,"ds":0,"flags":{},"sight":20,"light":20,"threshold":{"light":null,"sight":null,"sound":null,"attenuation":false}},
        {"_id":"Oh3bQYljqDJL38cG","c":[4550,2350,4550,2500],"move":20,"sound":20,"dir":0,"door":1,"ds":0,"flags":{},"sight":20,"light":20,"threshold":{"light":null,"sight":null,"sound":null,"attenuation":false}},
        {"_id":"DG9kTRXT3X10foN2","c":[4550,1600,4550,1750],"move":20,"sound":20,"dir":0,"door":1,"ds":0,"flags":{},"sight":20,"light":20,"threshold":{"light":null,"sight":null,"sound":null,"attenuation":false}},
        {"_id":"eiKARjVi1yRFCiho","c":[4550,1750,4550,1900],"move":20,"sound":20,"dir":0,"door":1,"ds":0,"flags":{},"sight":20,"light":20,"threshold":{"light":null,"sight":null,"sound":null,"attenuation":false}},
        {"_id":"sP0lMjkcmvUZyvxc","c":[3650,1600,3650,1750],"move":20,"sound":20,"dir":0,"door":1,"ds":0,"flags":{},"sight":20,"light":20,"threshold":{"light":null,"sight":null,"sound":null,"attenuation":false}},
        {"_id":"UnEOA2u7WU5vAdZE","c":[3650,1750,3650,1900],"move":20,"sound":20,"dir":0,"door":1,"ds":0,"flags":{},"sight":20,"light":20,"threshold":{"light":null,"sight":null,"sound":null,"attenuation":false}},
        {"_id":"9m7Yr1tbat2Z5jGN","c":[4550,1000,4550,1150],"move":20,"sound":20,"dir":0,"door":1,"ds":0,"flags":{},"sight":20,"light":20,"threshold":{"light":null,"sight":null,"sound":null,"attenuation":false}},
        {"_id":"1V9ADIiETwQpY98I","c":[4550,1150,4550,1300],"move":20,"sound":20,"dir":0,"door":1,"ds":0,"flags":{},"sight":20,"light":20,"threshold":{"light":null,"sight":null,"sound":null,"attenuation":false}},
        {"_id":"c17g8yueTxb0rVZ2","c":[3100,1450,3200,1450],"move":20,"sound":20,"dir":0,"door":1,"ds":0,"flags":{},"sight":20,"light":20,"threshold":{"light":null,"sight":null,"sound":null,"attenuation":false}},
        {"_id":"y9RWGMzoEZYa2kER","c":[3200,1450,3300,1450],"move":20,"sound":20,"dir":0,"door":1,"ds":0,"flags":{},"sight":20,"light":20,"threshold":{"light":null,"sight":null,"sound":null,"attenuation":false}},
        {"_id":"E5KPkArwnbs43NDY","c":[2050,1300,2050,1400],"move":20,"sound":20,"dir":0,"door":1,"ds":0,"flags":{},"sight":20,"light":20,"threshold":{"light":null,"sight":null,"sound":null,"attenuation":false}},
        {"_id":"ajhjkTF5savs8UQO","c":[2700,1100,2700,1200],"move":20,"sound":20,"dir":0,"door":2,"ds":0,"flags":{},"sight":20,"light":20,"threshold":{"light":null,"sight":null,"sound":null,"attenuation":false}},
        {"_id":"mR28vb4GU0RHpKxk","c":[2800,1100,2800,1200],"move":20,"sound":20,"dir":0,"door":2,"ds":0,"flags":{},"sight":20,"light":20,"threshold":{"light":null,"sight":null,"sound":null,"attenuation":false}},
        {"_id":"UGZmzRQZM4xvn49I","c":[3600,1000,3600,900],"move":20,"sound":20,"dir":0,"door":2,"ds":0,"flags":{},"sight":20,"light":20,"threshold":{"light":null,"sight":null,"sound":null,"attenuation":false}},
        {"_id":"PMc1m9TNO2PgmIQi","c":[3700,1000,3700,900],"move":20,"sound":20,"dir":0,"door":2,"ds":0,"flags":{},"sight":20,"light":20,"threshold":{"light":null,"sight":null,"sound":null,"attenuation":false}},
        {"_id":"wmZTpqgnsPSlrn6M","c":[950,600,950,3287],"move":20,"sound":20,"dir":0,"door":0,"ds":0,"flags":{},"sight":0,"light":0,"threshold":{"light":null,"sight":null,"sound":null,"attenuation":false}},
        {"_id":"hyAgvUPEdx5E0I1q","c":[950,3287,4862,3287],"move":20,"sound":20,"dir":0,"door":0,"ds":0,"flags":{},"sight":0,"light":0,"threshold":{"light":null,"sight":null,"sound":null,"attenuation":false}},
        {"_id":"B6RRE4z9pbuT7UQy","c":[4862,3287,4862,600],"move":20,"sound":20,"dir":0,"door":0,"ds":0,"flags":{},"sight":0,"light":0,"threshold":{"light":null,"sight":null,"sound":null,"attenuation":false}},
        {"_id":"Wh3EZUkZEhDhTBXy","c":[4862,600,950,600],"move":20,"sound":20,"dir":0,"door":0,"ds":0,"flags":{},"sight":0,"light":0,"threshold":{"light":null,"sight":null,"sound":null,"attenuation":false}}
    ],
    "lights": [
    
    ],
    "drawings": [
    
    ]
}
